Workbook

Sheet Como usar
A1: Controle de Custos da Lavoura
A2: Coleção Gestão no Campo • Instruções de uso
B4: Legenda de cores:
B5: Amarelo claro | C5: Células para você preencher (digitação livre ou lista suspensa).
B6: Cinza claro | C6: Fórmulas automáticas. Ficam protegidas para evitar que sejam apagadas por engano.
B7: Verde claro | C7: Linhas de total e resultados principais.
B9: Passo a passo
B10: Passo 1 | C10: Aba Config: cadastre a(s) safra(s) (ex.: 2025/26), a cultura e o preço esperado de venda em R$ por saca. Revise a lista de categorias de custo, o tipo (Variável/Fixo) e o grupo (Insumos, Operações, Mão de obra, Outros). Você pode renomear e incluir categorias nas linhas livres.
B11: Passo 2 | C11: Aba Talhões: para cada safra, cadastre os talhões com código (ex.: T01), área em hectares e produtividade esperada (sc/ha). Ao final da colheita, informe a produção realizada em sacas — a planilha passa a usar o realizado no lugar do esperado.
B12: Passo 3 | C12: Aba Lançamentos: registre cada gasto (insumos, operações, mão de obra, arrendamento etc.) com data, safra, talhão, categoria, quantidade e valor unitário. O valor total é calculado.
B13: Passo 4 | C13: Gastos que não pertencem a um talhão específico (ex.: salário fixo, diesel geral, assistência técnica) devem ser lançados no talhão 'GERAL': eles são rateados automaticamente entre os talhões da safra, proporcionalmente à área.
B14: Passo 5 | C14: Aba Painel: escolha a safra na célula amarela e veja área, custo total, custo por hectare, custo por saca, receita e resultado estimados, ponto de equilíbrio e gráficos por grupo e categoria.
B16: Indicadores calculados
B17: • | C17: Custo por hectare = custo total ÷ área (ha).
B18: • | C18: Custo por saca = custo total ÷ produção (realizada, ou esperada × área quando a realizada não foi informada). É também o preço mínimo de venda para empatar.
B19: • | C19: Ponto de equilíbrio (sc/ha) = custo por hectare ÷ preço esperado de venda: quantas sacas por hectare pagam o custo total.
B20: • | C20: Ponto de equilíbrio operacional = mesmo cálculo usando apenas os custos classificados como 'Variável' na aba Config.
B21: • | C21: 'Lançamentos sem talhão cadastrado' no Painel deve ser R$ 0,00. Se aparecer valor, há lançamento com código de talhão que não existe na aba Talhões para aquela safra.
B23: Dicas
B24: • | C24: Use sempre o mesmo código de talhão e o mesmo nome de safra (copie da lista suspensa).
B25: • | C25: Se você só tem o valor total de uma nota, lance quantidade 1 e o valor total como valor unitário.
B26: • | C26: Capacidade: 10 safras, 60 linhas de talhões, 20 categorias e 1.000 lançamentos.
B28: Proteção das planilhas
C29: As abas estão protegidas SEM SENHA apenas para evitar exclusão acidental de fórmulas. Para personalizar: Excel → guia Revisão → Desproteger Planilha (no LibreOffice: Ferramentas → Proteger planilha; no Google Planilhas a proteção não é importada). Lembre-se de proteger novamente depois.
C31: Compatível com Microsoft Excel 2010 ou superior, LibreOffice Calc e Google Planilhas. A aba 'Exemplo' contém apenas dados FICTÍCIOS para demonstração e pode ser excluída.

Sheet Painel
A1: Painel da Safra
A2: Resumo de custos, ponto de equilíbrio e resultado estimado
B5: Safra selecionada ▶ | C5: =IF(Config!A6="","",Config!A6)
B7: Indicadores da safra | E7: Custos por categoria
B8: Área total (ha) | C8: =SUMIFS('Talhões'!$D$6:$D$65,'Talhões'!$A$6:$A$65,$C$5) | E8: Categoria | F8: Grupo | G8: Tipo | H8: Valor (R$) | I8: R$/ha | J8: % do total
B9: Custo total da safra | C9: =SUMIFS('Lançamentos'!$J$6:$J$1005,'Lançamentos'!$B$6:$B$1005,$C$5) | E9: =IF(Config!$F6="","",Config!$F6) | F9: =IF(E9="","",Config!$H6) | G9: =IF(E9="","",Config!$G6) | H9: =IF(E9="","",SUMIFS('Lançamentos'!$J$6:$J$1005,'Lançamentos'!$B$6:$B$1005,$C$5,'Lançamentos'!$D$6:$D$1005,E9)) | I9: =IF(E9="","",IFERROR(H9/$C$8,0)) | J9: =IF(E9="","",IFERROR(H9/$C$9,0))
B10: Custo por hectare (R$/ha) | C10: =IFERROR(C9/C8,0) | E10: =IF(Config!$F7="","",Config!$F7) | F10: =IF(E10="","",Config!$H7) | G10: =IF(E10="","",Config!$G7) | H10: =IF(E10="","",SUMIFS('Lançamentos'!$J$6:$J$1005,'Lançamentos'!$B$6:$B$1005,$C$5,'Lançamentos'!$D$6:$D$1005,E10)) | I10: =IF(E10="","",IFERROR(H10/$C$8,0)) | J10: =IF(E10="","",IFERROR(H10/$C$9,0))
B11: Produção considerada (sacas) | C11: =SUMIFS('Talhões'!$K$6:$K$65,'Talhões'!$A$6:$A$65,$C$5) | E11: =IF(Config!$F8="","",Config!$F8) | F11: =IF(E11="","",Config!$H8) | G11: =IF(E11="","",Config!$G8) | H11: =IF(E11="","",SUMIFS('Lançamentos'!$J$6:$J$1005,'Lançamentos'!$B$6:$B$1005,$C$5,'Lançamentos'!$D$6:$D$1005,E11)) | I11: =IF(E11="","",IFERROR(H11/$C$8,0)) | J11: =IF(E11="","",IFERROR(H11/$C$9,0))
B12: Produtividade média (sc/ha) | C12: =IFERROR(C11/C8,0) | E12: =IF(Config!$F9="","",Config!$F9) | F12: =IF(E12="","",Config!$H9) | G12: =IF(E12="","",Config!$G9) | H12: =IF(E12="","",SUMIFS('Lançamentos'!$J$6:$J$1005,'Lançamentos'!$B$6:$B$1005,$C$5,'Lançamentos'!$D$6:$D$1005,E12)) | I12: =IF(E12="","",IFERROR(H12/$C$8,0)) | J12: =IF(E12="","",IFERROR(H12/$C$9,0))
B13: Custo por saca (R$/sc) | C13: =IFERROR(C9/C11,0) | E13: =IF(Config!$F10="","",Config!$F10) | F13: =IF(E13="","",Config!$H10) | G13: =IF(E13="","",Config!$G10) | H13: =IF(E13="","",SUMIFS('Lançamentos'!$J$6:$J$1005,'Lançamentos'!$B$6:$B$1005,$C$5,'Lançamentos'!$D$6:$D$1005,E13)) | I13: =IF(E13="","",IFERROR(H13/$C$8,0)) | J13: =IF(E13="","",IFERROR(H13/$C$9,0))
B14: Preço esperado de venda (R$/sc) | C14: =IFERROR(VLOOKUP($C$5,Config!$A$6:$C$15,3,0),0) | E14: =IF(Config!$F11="","",Config!$F11) | F14: =IF(E14="","",Config!$H11) | G14: =IF(E14="","",Config!$G11) | H14: =IF(E14="","",SUMIFS('Lançamentos'!$J$6:$J$1005,'Lançamentos'!$B$6:$B$1005,$C$5,'Lançamentos'!$D$6:$D$1005,E14)) | I14: =IF(E14="","",IFERROR(H14/$C$8,0)) | J14: =IF(E14="","",IFERROR(H14/$C$9,0))
B15: Receita estimada | C15: =C11*C14 | E15: =IF(Config!$F12="","",Config!$F12) | F15: =IF(E15="","",Config!$H12) | G15: =IF(E15="","",Config!$G12) | H15: =IF(E15="","",SUMIFS('Lançamentos'!$J$6:$J$1005,'Lançamentos'!$B$6:$B$1005,$C$5,'Lançamentos'!$D$6:$D$1005,E15)) | I15: =IF(E15="","",IFERROR(H15/$C$8,0)) | J15: =IF(E15="","",IFERROR(H15/$C$9,0))
B16: Resultado estimado | C16: =C15-C9 | E16: =IF(Config!$F13="","",Config!$F13) | F16: =IF(E16="","",Config!$H13) | G16: =IF(E16="","",Config!$G13) | H16: =IF(E16="","",SUMIFS('Lançamentos'!$J$6:$J$1005,'Lançamentos'!$B$6:$B$1005,$C$5,'Lançamentos'!$D$6:$D$1005,E16)) | I16: =IF(E16="","",IFERROR(H16/$C$8,0)) | J16: =IF(E16="","",IFERROR(H16/$C$9,0))
B17: Margem sobre a receita | C17: =IFERROR(C16/C15,0) | E17: =IF(Config!$F14="","",Config!$F14) | F17: =IF(E17="","",Config!$H14) | G17: =IF(E17="","",Config!$G14) | H17: =IF(E17="","",SUMIFS('Lançamentos'!$J$6:$J$1005,'Lançamentos'!$B$6:$B$1005,$C$5,'Lançamentos'!$D$6:$D$1005,E17)) | I17: =IF(E17="","",IFERROR(H17/$C$8,0)) | J17: =IF(E17="","",IFERROR(H17/$C$9,0))
B18: Ponto de equilíbrio (sc/ha) | C18: =IFERROR(C10/C14,0) | E18: =IF(Config!$F15="","",Config!$F15) | F18: =IF(E18="","",Config!$H15) | G18: =IF(E18="","",Config!$G15) | H18: =IF(E18="","",SUMIFS('Lançamentos'!$J$6:$J$1005,'Lançamentos'!$B$6:$B$1005,$C$5,'Lançamentos'!$D$6:$D$1005,E18)) | I18: =IF(E18="","",IFERROR(H18/$C$8,0)) | J18: =IF(E18="","",IFERROR(H18/$C$9,0))
B19: Ponto de equilíbrio (sacas na safra) | C19: =IFERROR(C9/C14,0) | E19: =IF(Config!$F16="","",Config!$F16) | F19: =IF(E19="","",Config!$H16) | G19: =IF(E19="","",Config!$G16) | H19: =IF(E19="","",SUMIFS('Lançamentos'!$J$6:$J$1005,'Lançamentos'!$B$6:$B$1005,$C$5,'Lançamentos'!$D$6:$D$1005,E19)) | I19: =IF(E19="","",IFERROR(H19/$C$8,0)) | J19: =IF(E19="","",IFERROR(H19/$C$9,0))
B20: Custo variável total | C20: =SUMIFS($H$9:$H$28,$G$9:$G$28,"Variável") | E20: =IF(Config!$F17="","",Config!$F17) | F20: =IF(E20="","",Config!$H17) | G20: =IF(E20="","",Config!$G17) | H20: =IF(E20="","",SUMIFS('Lançamentos'!$J$6:$J$1005,'Lançamentos'!$B$6:$B$1005,$C$5,'Lançamentos'!$D$6:$D$1005,E20)) | I20: =IF(E20="","",IFERROR(H20/$C$8,0)) | J20: =IF(E20="","",IFERROR(H20/$C$9,0))
B21: Ponto de equilíbrio operacional (sc/ha) | C21: =IFERROR(C20/C8/C14,0) | E21: =IF(Config!$F18="","",Config!$F18) | F21: =IF(E21="","",Config!$H18) | G21: =IF(E21="","",Config!$G18) | H21: =IF(E21="","",SUMIFS('Lançamentos'!$J$6:$J$1005,'Lançamentos'!$B$6:$B$1005,$C$5,'Lançamentos'!$D$6:$D$1005,E21)) | I21: =IF(E21="","",IFERROR(H21/$C$8,0)) | J21: =IF(E21="","",IFERROR(H21/$C$9,0))
B22: Lançamentos sem talhão cadastrado (R$) | C22: =ROUND(C9-SUMIFS('Talhões'!$I$6:$I$65,'Talhões'!$A$6:$A$65,$C$5),2) | E22: =IF(Config!$F19="","",Config!$F19) | F22: =IF(E22="","",Config!$H19) | G22: =IF(E22="","",Config!$G19) | H22: =IF(E22="","",SUMIFS('Lançamentos'!$J$6:$J$1005,'Lançamentos'!$B$6:$B$1005,$C$5,'Lançamentos'!$D$6:$D$1005,E22)) | I22: =IF(E22="","",IFERROR(H22/$C$8,0)) | J22: =IF(E22="","",IFERROR(H22/$C$9,0))
E23: =IF(Config!$F20="","",Config!$F20) | F23: =IF(E23="","",Config!$H20) | G23: =IF(E23="","",Config!$G20) | H23: =IF(E23="","",SUMIFS('Lançamentos'!$J$6:$J$1005,'Lançamentos'!$B$6:$B$1005,$C$5,'Lançamentos'!$D$6:$D$1005,E23)) | I23: =IF(E23="","",IFERROR(H23/$C$8,0)) | J23: =IF(E23="","",IFERROR(H23/$C$9,0))
E24: =IF(Config!$F21="","",Config!$F21) | F24: =IF(E24="","",Config!$H21) | G24: =IF(E24="","",Config!$G21) | H24: =IF(E24="","",SUMIFS('Lançamentos'!$J$6:$J$1005,'Lançamentos'!$B$6:$B$1005,$C$5,'Lançamentos'!$D$6:$D$1005,E24)) | I24: =IF(E24="","",IFERROR(H24/$C$8,0)) | J24: =IF(E24="","",IFERROR(H24/$C$9,0))
E25: =IF(Config!$F22="","",Config!$F22) | F25: =IF(E25="","",Config!$H22) | G25: =IF(E25="","",Config!$G22) | H25: =IF(E25="","",SUMIFS('Lançamentos'!$J$6:$J$1005,'Lançamentos'!$B$6:$B$1005,$C$5,'Lançamentos'!$D$6:$D$1005,E25)) | I25: =IF(E25="","",IFERROR(H25/$C$8,0)) | J25: =IF(E25="","",IFERROR(H25/$C$9,0))
E26: =IF(Config!$F23="","",Config!$F23) | F26: =IF(E26="","",Config!$H23) | G26: =IF(E26="","",Config!$G23) | H26: =IF(E26="","",SUMIFS('Lançamentos'!$J$6:$J$1005,'Lançamentos'!$B$6:$B$1005,$C$5,'Lançamentos'!$D$6:$D$1005,E26)) | I26: =IF(E26="","",IFERROR(H26/$C$8,0)) | J26: =IF(E26="","",IFERROR(H26/$C$9,0))
E27: =IF(Config!$F24="","",Config!$F24) | F27: =IF(E27="","",Config!$H24) | G27: =IF(E27="","",Config!$G24) | H27: =IF(E27="","",SUMIFS('Lançamentos'!$J$6:$J$1005,'Lançamentos'!$B$6:$B$1005,$C$5,'Lançamentos'!$D$6:$D$1005,E27)) | I27: =IF(E27="","",IFERROR(H27/$C$8,0)) | J27: =IF(E27="","",IFERROR(H27/$C$9,0))
E28: =IF(Config!$F25="","",Config!$F25) | F28: =IF(E28="","",Config!$H25) | G28: =IF(E28="","",Config!$G25) | H28: =IF(E28="","",SUMIFS('Lançamentos'!$J$6:$J$1005,'Lançamentos'!$B$6:$B$1005,$C$5,'Lançamentos'!$D$6:$D$1005,E28)) | I28: =IF(E28="","",IFERROR(H28/$C$8,0)) | J28: =IF(E28="","",IFERROR(H28/$C$9,0))
E29: TOTAL | H29: =SUM(H9:H28) | I29: =IFERROR(H29/$C$8,0) | J29: =IFERROR(H29/$C$9,0)
E31: Custos por grupo
E32: Grupo | H32: Valor (R$) | I32: R$/ha | J32: % do total
E33: Insumos | H33: =SUMIFS('Lançamentos'!$J$6:$J$1005,'Lançamentos'!$B$6:$B$1005,$C$5,'Lançamentos'!$E$6:$E$1005,E33) | I33: =IFERROR(H33/$C$8,0) | J33: =IFERROR(H33/$C$9,0)
E34: Operações | H34: =SUMIFS('Lançamentos'!$J$6:$J$1005,'Lançamentos'!$B$6:$B$1005,$C$5,'Lançamentos'!$E$6:$E$1005,E34) | I34: =IFERROR(H34/$C$8,0) | J34: =IFERROR(H34/$C$9,0)
E35: Mão de obra | H35: =SUMIFS('Lançamentos'!$J$6:$J$1005,'Lançamentos'!$B$6:$B$1005,$C$5,'Lançamentos'!$E$6:$E$1005,E35) | I35: =IFERROR(H35/$C$8,0) | J35: =IFERROR(H35/$C$9,0)
E36: Outros | H36: =SUMIFS('Lançamentos'!$J$6:$J$1005,'Lançamentos'!$B$6:$B$1005,$C$5,'Lançamentos'!$E$6:$E$1005,E36) | I36: =IFERROR(H36/$C$8,0) | J36: =IFERROR(H36/$C$9,0)
E37: TOTAL | H37: =SUM(H33:H36) | I37: =IFERROR(H37/$C$8,0) | J37: =IFERROR(H37/$C$9,0)

Sheet Config
A1: Configurações
A2: Safras, preços esperados e categorias de custo
A3: Legenda: | B3: Preencher | C3: Cálculo automático (protegido)
A4: Safras | F4: Categorias de custo
A5: Safra | B5: Cultura | C5: Preço esperado de venda (R$/saca) | F5: Categoria | G5: Tipo de custo | H5: Grupo
F6: Sementes | G6: Variável | H6: Insumos
F7: Fertilizantes e corretivos | G7: Variável | H7: Insumos
F8: Defensivos | G8: Variável | H8: Insumos
F9: Inoculantes e adjuvantes | G9: Variável | H9: Insumos
F10: Operações mecanizadas próprias | G10: Variável | H10: Operações
F11: Serviços terceirizados | G11: Variável | H11: Operações
F12: Combustíveis e lubrificantes | G12: Variável | H12: Operações
F13: Manutenção de máquinas | G13: Variável | H13: Operações
F14: Mão de obra fixa | G14: Fixo | H14: Mão de obra
F15: Mão de obra temporária/diárias | G15: Variável | H15: Mão de obra
F16: Arrendamento da terra | G16: Fixo | H16: Outros
A17: Dica: escreva a safra como texto, ex.: 2025/26. | F17: Assistência técnica | G17: Fixo | H17: Outros
F18: Seguro agrícola | G18: Variável | H18: Outros
F19: Frete e armazenagem | G19: Variável | H19: Outros
F20: Juros de custeio | G20: Variável | H20: Outros
F21: Depreciação | G21: Fixo | H21: Outros
F22: Outros custos | G22: Variável | H22: Outros

Sheet Talhões
A1: Talhões
A2: Cadastro de talhões por safra e resultado por talhão
A3: Legenda: | B3: Preencher | C3: Cálculo automático (protegido)
A5: Safra | B5: Código do talhão | C5: Nome / descrição | D5: Área (ha) | E5: Produtividade esperada (sc/ha) | F5: Produção realizada (sacas) | G5: Custo direto (R$) | H5: Rateio custos GERAL (R$) | I5: Custo total (R$) | J5: Custo por hectare (R$/ha) | K5: Produção considerada (sacas) | L5: Custo por saca (R$/sc) | M5: Receita estimada (R$) | N5: Resultado estimado (R$) | O5: Ponto de equilíbrio (sc/ha)
G6: =IF(OR($A6="",$B6=""),"",SUMIFS('Lançamentos'!$J$6:$J$1005,'Lançamentos'!$B$6:$B$1005,$A6,'Lançamentos'!$C$6:$C$1005,$B6)) | H6: =IF(OR($A6="",$B6=""),"",IFERROR(SUMIFS('Lançamentos'!$J$6:$J$1005,'Lançamentos'!$B$6:$B$1005,$A6,'Lançamentos'!$C$6:$C$1005,"GERAL")*N($D6)/SUMIFS($D$6:$D$65,$A$6:$A$65,$A6),0)) | I6: =IF(OR($A6="",$B6=""),"",G6+H6) | J6: =IF(OR($A6="",$B6=""),"",IFERROR(I6/D6,0)) | K6: =IF(OR($A6="",$B6=""),"",IF(N(F6)>0,F6,N(E6)*N(D6))) | L6: =IF(OR($A6="",$B6=""),"",IFERROR(I6/K6,0)) | M6: =IF(OR($A6="",$B6=""),"",K6*IFERROR(VLOOKUP($A6,Config!$A$6:$C$15,3,0),0)) | N6: =IF(OR($A6="",$B6=""),"",M6-I6) | O6: =IF(OR($A6="",$B6=""),"",IFERROR(J6/IFERROR(VLOOKUP($A6,Config!$A$6:$C$15,3,0),0),0))
G7: =IF(OR($A7="",$B7=""),"",SUMIFS('Lançamentos'!$J$6:$J$1005,'Lançamentos'!$B$6:$B$1005,$A7,'Lançamentos'!$C$6:$C$1005,$B7)) | H7: =IF(OR($A7="",$B7=""),"",IFERROR(SUMIFS('Lançamentos'!$J$6:$J$1005,'Lançamentos'!$B$6:$B$1005,$A7,'Lançamentos'!$C$6:$C$1005,"GERAL")*N($D7)/SUMIFS($D$6:$D$65,$A$6:$A$65,$A7),0)) | I7: =IF(OR($A7="",$B7=""),"",G7+H7) | J7: =IF(OR($A7="",$B7=""),"",IFERROR(I7/D7,0)) | K7: =IF(OR($A7="",$B7=""),"",IF(N(F7)>0,F7,N(E7)*N(D7))) | L7: =IF(OR($A7="",$B7=""),"",IFERROR(I7/K7,0)) | M7: =IF(OR($A7="",$B7=""),"",K7*IFERROR(VLOOKUP($A7,Config!$A$6:$C$15,3,0),0)) | N7: =IF(OR($A7="",$B7=""),"",M7-I7) | O7: =IF(OR($A7="",$B7=""),"",IFERROR(J7/IFERROR(VLOOKUP($A7,Config!$A$6:$C$15,3,0),0),0))
G8: =IF(OR($A8="",$B8=""),"",SUMIFS('Lançamentos'!$J$6:$J$1005,'Lançamentos'!$B$6:$B$1005,$A8,'Lançamentos'!$C$6:$C$1005,$B8)) | H8: =IF(OR($A8="",$B8=""),"",IFERROR(SUMIFS('Lançamentos'!$J$6:$J$1005,'Lançamentos'!$B$6:$B$1005,$A8,'Lançamentos'!$C$6:$C$1005,"GERAL")*N($D8)/SUMIFS($D$6:$D$65,$A$6:$A$65,$A8),0)) | I8: =IF(OR($A8="",$B8=""),"",G8+H8) | J8: =IF(OR($A8="",$B8=""),"",IFERROR(I8/D8,0)) | K8: =IF(OR($A8="",$B8=""),"",IF(N(F8)>0,F8,N(E8)*N(D8))) | L8: =IF(OR($A8="",$B8=""),"",IFERROR(I8/K8,0)) | M8: =IF(OR($A8="",$B8=""),"",K8*IFERROR(VLOOKUP($A8,Config!$A$6:$C$15,3,0),0)) | N8: =IF(OR($A8="",$B8=""),"",M8-I8) | O8: =IF(OR($A8="",$B8=""),"",IFERROR(J8/IFERROR(VLOOKUP($A8,Config!$A$6:$C$15,3,0),0),0))
G9: =IF(OR($A9="",$B9=""),"",SUMIFS('Lançamentos'!$J$6:$J$1005,'Lançamentos'!$B$6:$B$1005,$A9,'Lançamentos'!$C$6:$C$1005,$B9)) | H9: =IF(OR($A9="",$B9=""),"",IFERROR(SUMIFS('Lançamentos'!$J$6:$J$1005,'Lançamentos'!$B$6:$B$1005,$A9,'Lançamentos'!$C$6:$C$1005,"GERAL")*N($D9)/SUMIFS($D$6:$D$65,$A$6:$A$65,$A9),0)) | I9: =IF(OR($A9="",$B9=""),"",G9+H9) | J9: =IF(OR($A9="",$B9=""),"",IFERROR(I9/D9,0)) | K9: =IF(OR($A9="",$B9=""),"",IF(N(F9)>0,F9,N(E9)*N(D9))) | L9: =IF(OR($A9="",$B9=""),"",IFERROR(I9/K9,0)) | M9: =IF(OR($A9="",$B9=""),"",K9*IFERROR(VLOOKUP($A9,Config!$A$6:$C$15,3,0),0)) | N9: =IF(OR($A9="",$B9=""),"",M9-I9) | O9: =IF(OR($A9="",$B9=""),"",IFERROR(J9/IFERROR(VLOOKUP($A9,Config!$A$6:$C$15,3,0),0),0))
G10: =IF(OR($A10="",$B10=""),"",SUMIFS('Lançamentos'!$J$6:$J$1005,'Lançamentos'!$B$6:$B$1005,$A10,'Lançamentos'!$C$6:$C$1005,$B10)) | H10: =IF(OR($A10="",$B10=""),"",IFERROR(SUMIFS('Lançamentos'!$J$6:$J$1005,'Lançamentos'!$B$6:$B$1005,$A10,'Lançamentos'!$C$6:$C$1005,"GERAL")*N($D10)/SUMIFS($D$6:$D$65,$A$6:$A$65,$A10),0)) | I10: =IF(OR($A10="",$B10=""),"",G10+H10) | J10: =IF(OR($A10="",$B10=""),"",IFERROR(I10/D10,0)) | K10: =IF(OR($A10="",$B10=""),"",IF(N(F10)>0,F10,N(E10)*N(D10))) | L10: =IF(OR($A10="",$B10=""),"",IFERROR(I10/K10,0)) | M10: =IF(OR($A10="",$B10=""),"",K10*IFERROR(VLOOKUP($A10,Config!$A$6:$C$15,3,0),0)) | N10: =IF(OR($A10="",$B10=""),"",M10-I10) | O10: =IF(OR($A10="",$B10=""),"",IFERROR(J10/IFERROR(VLOOKUP($A10,Config!$A$6:$C$15,3,0),0),0))
G11: =IF(OR($A11="",$B11=""),"",SUMIFS('Lançamentos'!$J$6:$J$1005,'Lançamentos'!$B$6:$B$1005,$A11,'Lançamentos'!$C$6:$C$1005,$B11)) | H11: =IF(OR($A11="",$B11=""),"",IFERROR(SUMIFS('Lançamentos'!$J$6:$J$1005,'Lançamentos'!$B$6:$B$1005,$A11,'Lançamentos'!$C$6:$C$1005,"GERAL")*N($D11)/SUMIFS($D$6:$D$65,$A$6:$A$65,$A11),0)) | I11: =IF(OR($A11="",$B11=""),"",G11+H11) | J11: =IF(OR($A11="",$B11=""),"",IFERROR(I11/D11,0)) | K11: =IF(OR($A11="",$B11=""),"",IF(N(F11)>0,F11,N(E11)*N(D11))) | L11: =IF(OR($A11="",$B11=""),"",IFERROR(I11/K11,0)) | M11: =IF(OR($A11="",$B11=""),"",K11*IFERROR(VLOOKUP($A11,Config!$A$6:$C$15,3,0),0)) | N11: =IF(OR($A11="",$B11=""),"",M11-I11) | O11: =IF(OR($A11="",$B11=""),"",IFERROR(J11/IFERROR(VLOOKUP($A11,Config!$A$6:$C$15,3,0),0),0))
G12: =IF(OR($A12="",$B12=""),"",SUMIFS('Lançamentos'!$J$6:$J$1005,'Lançamentos'!$B$6:$B$1005,$A12,'Lançamentos'!$C$6:$C$1005,$B12)) | H12: =IF(OR($A12="",$B12=""),"",IFERROR(SUMIFS('Lançamentos'!$J$6:$J$1005,'Lançamentos'!$B$6:$B$1005,$A12,'Lançamentos'!$C$6:$C$1005,"GERAL")*N($D12)/SUMIFS($D$6:$D$65,$A$6:$A$65,$A12),0)) | I12: =IF(OR($A12="",$B12=""),"",G12+H12) | J12: =IF(OR($A12="",$B12=""),"",IFERROR(I12/D12,0)) | K12: =IF(OR($A12="",$B12=""),"",IF(N(F12)>0,F12,N(E12)*N(D12))) | L12: =IF(OR($A12="",$B12=""),"",IFERROR(I12/K12,0)) | M12: =IF(OR($A12="",$B12=""),"",K12*IFERROR(VLOOKUP($A12,Config!$A$6:$C$15,3,0),0)) | N12: =IF(OR($A12="",$B12=""),"",M12-I12) | O12: =IF(OR($A12="",$B12=""),"",IFERROR(J12/IFERROR(VLOOKUP($A12,Config!$A$6:$C$15,3,0),0),0))
G13: =IF(OR($A13="",$B13=""),"",SUMIFS('Lançamentos'!$J$6:$J$1005,'Lançamentos'!$B$6:$B$1005,$A13,'Lançamentos'!$C$6:$C$1005,$B13)) | H13: =IF(OR($A13="",$B13=""),"",IFERROR(SUMIFS('Lançamentos'!$J$6:$J$1005,'Lançamentos'!$B$6:$B$1005,$A13,'Lançamentos'!$C$6:$C$1005,"GERAL")*N($D13)/SUMIFS($D$6:$D$65,$A$6:$A$65,$A13),0)) | I13: =IF(OR($A13="",$B13=""),"",G13+H13) | J13: =IF(OR($A13="",$B13=""),"",IFERROR(I13/D13,0)) | K13: =IF(OR($A13="",$B13=""),"",IF(N(F13)>0,F13,N(E13)*N(D13))) | L13: =IF(OR($A13="",$B13=""),"",IFERROR(I13/K13,0)) | M13: =IF(OR($A13="",$B13=""),"",K13*IFERROR(VLOOKUP($A13,Config!$A$6:$C$15,3,0),0)) | N13: =IF(OR($A13="",$B13=""),"",M13-I13) | O13: =IF(OR($A13="",$B13=""),"",IFERROR(J13/IFERROR(VLOOKUP($A13,Config!$A$6:$C$15,3,0),0),0))
G14: =IF(OR($A14="",$B14=""),"",SUMIFS('Lançamentos'!$J$6:$J$1005,'Lançamentos'!$B$6:$B$1005,$A14,'Lançamentos'!$C$6:$C$1005,$B14)) | H14: =IF(OR($A14="",$B14=""),"",IFERROR(SUMIFS('Lançamentos'!$J$6:$J$1005,'Lançamentos'!$B$6:$B$1005,$A14,'Lançamentos'!$C$6:$C$1005,"GERAL")*N($D14)/SUMIFS($D$6:$D$65,$A$6:$A$65,$A14),0)) | I14: =IF(OR($A14="",$B14=""),"",G14+H14) | J14: =IF(OR($A14="",$B14=""),"",IFERROR(I14/D14,0)) | K14: =IF(OR($A14="",$B14=""),"",IF(N(F14)>0,F14,N(E14)*N(D14))) | L14: =IF(OR($A14="",$B14=""),"",IFERROR(I14/K14,0)) | M14: =IF(OR($A14="",$B14=""),"",K14*IFERROR(VLOOKUP($A14,Config!$A$6:$C$15,3,0),0)) | N14: =IF(OR($A14="",$B14=""),"",M14-I14) | O14: =IF(OR($A14="",$B14=""),"",IFERROR(J14/IFERROR(VLOOKUP($A14,Config!$A$6:$C$15,3,0),0),0))
G15: =IF(OR($A15="",$B15=""),"",SUMIFS('Lançamentos'!$J$6:$J$1005,'Lançamentos'!$B$6:$B$1005,$A15,'Lançamentos'!$C$6:$C$1005,$B15)) | H15: =IF(OR($A15="",$B15=""),"",IFERROR(SUMIFS('Lançamentos'!$J$6:$J$1005,'Lançamentos'!$B$6:$B$1005,$A15,'Lançamentos'!$C$6:$C$1005,"GERAL")*N($D15)/SUMIFS($D$6:$D$65,$A$6:$A$65,$A15),0)) | I15: =IF(OR($A15="",$B15=""),"",G15+H15) | J15: =IF(OR($A15="",$B15=""),"",IFERROR(I15/D15,0)) | K15: =IF(OR($A15="",$B15=""),"",IF(N(F15)>0,F15,N(E15)*N(D15))) | L15: =IF(OR($A15="",$B15=""),"",IFERROR(I15/K15,0)) | M15: =IF(OR($A15="",$B15=""),"",K15*IFERROR(VLOOKUP($A15,Config!$A$6:$C$15,3,0),0)) | N15: =IF(OR($A15="",$B15=""),"",M15-I15) | O15: =IF(OR($A15="",$B15=""),"",IFERROR(J15/IFERROR(VLOOKUP($A15,Config!$A$6:$C$15,3,0),0),0))
G16: =IF(OR($A16="",$B16=""),"",SUMIFS('Lançamentos'!$J$6:$J$1005,'Lançamentos'!$B$6:$B$1005,$A16,'Lançamentos'!$C$6:$C$1005,$B16)) | H16: =IF(OR($A16="",$B16=""),"",IFERROR(SUMIFS('Lançamentos'!$J$6:$J$1005,'Lançamentos'!$B$6:$B$1005,$A16,'Lançamentos'!$C$6:$C$1005,"GERAL")*N($D16)/SUMIFS($D$6:$D$65,$A$6:$A$65,$A16),0)) | I16: =IF(OR($A16="",$B16=""),"",G16+H16) | J16: =IF(OR($A16="",$B16=""),"",IFERROR(I16/D16,0)) | K16: =IF(OR($A16="",$B16=""),"",IF(N(F16)>0,F16,N(E16)*N(D16))) | L16: =IF(OR($A16="",$B16=""),"",IFERROR(I16/K16,0)) | M16: =IF(OR($A16="",$B16=""),"",K16*IFERROR(VLOOKUP($A16,Config!$A$6:$C$15,3,0),0)) | N16: =IF(OR($A16="",$B16=""),"",M16-I16) | O16: =IF(OR($A16="",$B16=""),"",IFERROR(J16/IFERROR(VLOOKUP($A16,Config!$A$6:$C$15,3,0),0),0))
G17: =IF(OR($A17="",$B17=""),"",SUMIFS('Lançamentos'!$J$6:$J$1005,'Lançamentos'!$B$6:$B$1005,$A17,'Lançamentos'!$C$6:$C$1005,$B17)) | H17: =IF(OR($A17="",$B17=""),"",IFERROR(SUMIFS('Lançamentos'!$J$6:$J$1005,'Lançamentos'!$B$6:$B$1005,$A17,'Lançamentos'!$C$6:$C$1005,"GERAL")*N($D17)/SUMIFS($D$6:$D$65,$A$6:$A$65,$A17),0)) | I17: =IF(OR($A17="",$B17=""),"",G17+H17) | J17: =IF(OR($A17="",$B17=""),"",IFERROR(I17/D17,0)) | K17: =IF(OR($A17="",$B17=""),"",IF(N(F17)>0,F17,N(E17)*N(D17))) | L17: =IF(OR($A17="",$B17=""),"",IFERROR(I17/K17,0)) | M17: =IF(OR($A17="",$B17=""),"",K17*IFERROR(VLOOKUP($A17,Config!$A$6:$C$15,3,0),0)) | N17: =IF(OR($A17="",$B17=""),"",M17-I17) | O17: =IF(OR($A17="",$B17=""),"",IFERROR(J17/IFERROR(VLOOKUP($A17,Config!$A$6:$C$15,3,0),0),0))
... G65: =IF(OR($A65="",$B65=""),"",SUMIFS('Lançamentos'!$J$6:$J$1005,'Lançamentos'!$B$6:$B$1005,$A65,'Lançamentos'!$C$6:$C$1005,$B65)) | H65: =IF(OR($A65="",$B65=""),"",IFERROR(SUMIFS('Lançamentos'!$J$6:$J$1005,'Lançamentos'!$B$6:$B$1005,$A65,'Lançamentos'!$C$6:$C$1005,"GERAL")*N($D65)/SUMIFS($D$6:$D$65,$A$6:$A$65,$A65),0)) | I65: =IF(OR($A65="",$B65=""),"",G65+H65) | J65: =IF(OR($A65="",$B65=""),"",IFERROR(I65/D65,0)) | K65: =IF(OR($A65="",$B65=""),"",IF(N(F65)>0,F65,N(E65)*N(D65))) | L65: =IF(OR($A65="",$B65=""),"",IFERROR(I65/K65,0)) | M65: =IF(OR($A65="",$B65=""),"",K65*IFERROR(VLOOKUP($A65,Config!$A$6:$C$15,3,0),0)) | N65: =IF(OR($A65="",$B65=""),"",M65-I65) | O65: =IF(OR($A65="",$B65=""),"",IFERROR(J65/IFERROR(VLOOKUP($A65,Config!$A$6:$C$15,3,0),0),0))

Sheet Lançamentos
A1: Lançamentos de Custos
A2: Insumos, operações, mão de obra e demais gastos da safra
A3: Legenda: | B3: Preencher | C3: Cálculo automático (protegido)
A5: Data | B5: Safra | C5: Talhão | D5: Categoria | E5: Grupo | F5: Descrição / produto | G5: Quantidade | H5: Unidade | I5: Valor unitário (R$) | J5: Valor total (R$) | K5: Fornecedor / observação
E6: =IF(D6="","",IFERROR(VLOOKUP(D6,Config!$F$6:$H$25,3,0),"Categoria inválida")) | J6: =IF(OR(G6="",I6=""),"",G6*I6)
E7: =IF(D7="","",IFERROR(VLOOKUP(D7,Config!$F$6:$H$25,3,0),"Categoria inválida")) | J7: =IF(OR(G7="",I7=""),"",G7*I7)
E8: =IF(D8="","",IFERROR(VLOOKUP(D8,Config!$F$6:$H$25,3,0),"Categoria inválida")) | J8: =IF(OR(G8="",I8=""),"",G8*I8)
E9: =IF(D9="","",IFERROR(VLOOKUP(D9,Config!$F$6:$H$25,3,0),"Categoria inválida")) | J9: =IF(OR(G9="",I9=""),"",G9*I9)
E10: =IF(D10="","",IFERROR(VLOOKUP(D10,Config!$F$6:$H$25,3,0),"Categoria inválida")) | J10: =IF(OR(G10="",I10=""),"",G10*I10)
E11: =IF(D11="","",IFERROR(VLOOKUP(D11,Config!$F$6:$H$25,3,0),"Categoria inválida")) | J11: =IF(OR(G11="",I11=""),"",G11*I11)
E12: =IF(D12="","",IFERROR(VLOOKUP(D12,Config!$F$6:$H$25,3,0),"Categoria inválida")) | J12: =IF(OR(G12="",I12=""),"",G12*I12)
E13: =IF(D13="","",IFERROR(VLOOKUP(D13,Config!$F$6:$H$25,3,0),"Categoria inválida")) | J13: =IF(OR(G13="",I13=""),"",G13*I13)
E14: =IF(D14="","",IFERROR(VLOOKUP(D14,Config!$F$6:$H$25,3,0),"Categoria inválida")) | J14: =IF(OR(G14="",I14=""),"",G14*I14)
E15: =IF(D15="","",IFERROR(VLOOKUP(D15,Config!$F$6:$H$25,3,0),"Categoria inválida")) | J15: =IF(OR(G15="",I15=""),"",G15*I15)
E16: =IF(D16="","",IFERROR(VLOOKUP(D16,Config!$F$6:$H$25,3,0),"Categoria inválida")) | J16: =IF(OR(G16="",I16=""),"",G16*I16)
E17: =IF(D17="","",IFERROR(VLOOKUP(D17,Config!$F$6:$H$25,3,0),"Categoria inválida")) | J17: =IF(OR(G17="",I17=""),"",G17*I17)
... E1005: =IF(D1005="","",IFERROR(VLOOKUP(D1005,Config!$F$6:$H$25,3,0),"Categoria inválida")) | J1005: =IF(OR(G1005="",I1005=""),"",G1005*I1005)

Sheet Listas
A1: Talhões | B1: Grupos | C1: Unidades
A2: GERAL | B2: Insumos | C2: kg
A3: =IF('Talhões'!B6="","",'Talhões'!B6) | B3: Operações | C3: t
A4: =IF('Talhões'!B7="","",'Talhões'!B7) | B4: Mão de obra | C4: L
A5: =IF('Talhões'!B8="","",'Talhões'!B8) | B5: Outros | C5: sc
A6: =IF('Talhões'!B9="","",'Talhões'!B9) | C6: ha
A7: =IF('Talhões'!B10="","",'Talhões'!B10) | C7: h
A8: =IF('Talhões'!B11="","",'Talhões'!B11) | C8: diária
A9: =IF('Talhões'!B12="","",'Talhões'!B12) | C9: mês
A10: =IF('Talhões'!B13="","",'Talhões'!B13) | C10: un
A11: =IF('Talhões'!B14="","",'Talhões'!B14) | C11: serviço
A12: =IF('Talhões'!B15="","",'Talhões'!B15) | C12: km
A13: =IF('Talhões'!B16="","",'Talhões'!B16)
A14: =IF('Talhões'!B17="","",'Talhões'!B17)
A15: =IF('Talhões'!B18="","",'Talhões'!B18)
A16: =IF('Talhões'!B19="","",'Talhões'!B19)
A17: =IF('Talhões'!B20="","",'Talhões'!B20)
A18: =IF('Talhões'!B21="","",'Talhões'!B21)
A19: =IF('Talhões'!B22="","",'Talhões'!B22)
A20: =IF('Talhões'!B23="","",'Talhões'!B23)
A21: =IF('Talhões'!B24="","",'Talhões'!B24)
A22: =IF('Talhões'!B25="","",'Talhões'!B25)
A23: =IF('Talhões'!B26="","",'Talhões'!B26)
A24: =IF('Talhões'!B27="","",'Talhões'!B27)
... A62: =IF('Talhões'!B65="","",'Talhões'!B65)

Sheet Exemplo
A1: Exemplo preenchido (dados fictícios)
A2: Veja como a planilha funciona antes de lançar seus dados
A3: EXEMPLO — TODOS OS DADOS DESTA ABA SÃO FICTÍCIOS, criados apenas para demonstrar o funcionamento. Não use como referência de preços, custos ou produtividade.
A5: Safra: | B5: 2025/26 (exemplo)
A6: Preço R$/sc: | B6: 120
A8: Talhões (exemplo)
A9: Código | B9: Nome | C9: Área (ha) | D9: Prod. esperada (sc/ha) | E9: Produção realizada (sc) | F9: Custo direto (R$) | G9: Rateio GERAL (R$) | H9: Custo total (R$) | I9: Custo/ha (R$) | J9: Produção considerada (sc) | K9: Custo/saca (R$) | L9: Receita estimada (R$) | M9: Resultado (R$) | N9: Ponto equilíbrio (sc/ha)
A10: T01 | B10: Talhão Sede | C10: 50 | D10: 62 | E10: 3050 | F10: =SUMIF($B$17:$B$33,A10,$I$17:$I$33) | G10: =IFERROR(SUMIF($B$17:$B$33,"GERAL",$I$17:$I$33)*C10/SUM($C$10:$C$12),0) | H10: =F10+G10 | I10: =IFERROR(H10/C10,0) | J10: =IF(N(E10)>0,E10,D10*C10) | K10: =IFERROR(H10/J10,0) | L10: =J10*$B$6 | M10: =L10-H10 | N10: =IFERROR(I10/$B$6,0)
A11: T02 | B11: Talhão Baixada | C11: 35 | D11: 58 | F11: =SUMIF($B$17:$B$33,A11,$I$17:$I$33) | G11: =IFERROR(SUMIF($B$17:$B$33,"GERAL",$I$17:$I$33)*C11/SUM($C$10:$C$12),0) | H11: =F11+G11 | I11: =IFERROR(H11/C11,0) | J11: =IF(N(E11)>0,E11,D11*C11) | K11: =IFERROR(H11/J11,0) | L11: =J11*$B$6 | M11: =L11-H11 | N11: =IFERROR(I11/$B$6,0)
A12: T03 | B12: Talhão Divisa | C12: 15 | D12: 55 | E12: 800 | F12: =SUMIF($B$17:$B$33,A12,$I$17:$I$33) | G12: =IFERROR(SUMIF($B$17:$B$33,"GERAL",$I$17:$I$33)*C12/SUM($C$10:$C$12),0) | H12: =F12+G12 | I12: =IFERROR(H12/C12,0) | J12: =IF(N(E12)>0,E12,D12*C12) | K12: =IFERROR(H12/J12,0) | L12: =J12*$B$6 | M12: =L12-H12 | N12: =IFERROR(I12/$B$6,0)
A13: TOTAL | C13: =SUM(C10:C12) | F13: =SUM(F10:F12) | G13: =SUM(G10:G12) | H13: =SUM(H10:H12) | I13: =IFERROR(H13/C13,0) | J13: =SUM(J10:J12) | K13: =IFERROR(H13/J13,0) | L13: =SUM(L10:L12) | M13: =SUM(M10:M12) | N13: =IFERROR(I13/$B$6,0)
A15: Lançamentos (exemplo)
A16: Data | B16: Talhão | C16: Categoria | D16: Grupo | E16: Descrição | F16: Quantidade | G16: Unidade | H16: Valor unitário (R$) | I16: Valor total (R$)
A17: 45920 | B17: T01 | C17: Sementes | D17: Insumos | E17: Semente de soja | F17: 50 | G17: sc | H17: 600 | I17: =F17*H17
A18: 45920 | B18: T02 | C18: Sementes | D18: Insumos | E18: Semente de soja | F18: 35 | G18: sc | H18: 600 | I18: =F18*H18
A19: 45921 | B19: T03 | C19: Sementes | D19: Insumos | E19: Semente de soja | F19: 15 | G19: sc | H19: 600 | I19: =F19*H19
A20: 45925 | B20: T01 | C20: Fertilizantes e corretivos | D20: Insumos | E20: Adubo formulado | F20: 25 | G20: t | H20: 3200 | I20: =F20*H20
A21: 45925 | B21: T02 | C21: Fertilizantes e corretivos | D21: Insumos | E21: Adubo formulado | F21: 17.5 | G21: t | H21: 3200 | I21: =F21*H21
A22: 45926 | B22: T03 | C22: Fertilizantes e corretivos | D22: Insumos | E22: Adubo formulado | F22: 7.5 | G22: t | H22: 3200 | I22: =F22*H22
A23: 45971 | B23: T01 | C23: Defensivos | D23: Insumos | E23: Herbicida/fungicida | F23: 500 | G23: L | H23: 160 | I23: =F23*H23
A24: 45971 | B24: T02 | C24: Defensivos | D24: Insumos | E24: Herbicida/fungicida | F24: 350 | G24: L | H24: 160 | I24: =F24*H24
A25: 45972 | B25: T03 | C25: Defensivos | D25: Insumos | E25: Herbicida/fungicida | F25: 150 | G25: L | H25: 160 | I25: =F25*H25
A26: 46006 | B26: GERAL | C26: Combustíveis e lubrificantes | D26: Operações | E26: Diesel | F26: 6000 | G26: L | H26: 6.1 | I26: =F26*H26
A27: 46073 | B27: T01 | C27: Serviços terceirizados | D27: Operações | E27: Colheita terceirizada | F27: 50 | G27: ha | H27: 350 | I27: =F27*H27
A28: 46075 | B28: T02 | C28: Serviços terceirizados | D28: Operações | E28: Colheita terceirizada | F28: 35 | G28: ha | H28: 350 | I28: =F28*H28
... A33: 46096 | B33: GERAL | C33: Assistência técnica | D33: Outros | E33: Consultoria agronômica | F33: 1 | G33: serviço | H33: 9000 | I33: =F33*H33
A34: TOTAL | I34: =SUM(I17:I33)
A36: Resumo da safra (exemplo) | E36: Custo por grupo (exemplo)
A37: • | B37: Área total (ha) | C37: =C13 | E37: Insumos | F37: =SUMIF($D$17:$D$33,E37,$I$17:$I$33) | G37: =IFERROR(F37/$I$34,0)
A38: • | B38: Custo total | C38: =I34 | E38: Operações | F38: =SUMIF($D$17:$D$33,E38,$I$17:$I$33) | G38: =IFERROR(F38/$I$34,0)
A39: • | B39: Custo por hectare | C39: =IFERROR(H13/C13,0) | E39: Mão de obra | F39: =SUMIF($D$17:$D$33,E39,$I$17:$I$33) | G39: =IFERROR(F39/$I$34,0)
A40: • | B40: Produção considerada (sc) | C40: =J13 | E40: Outros | F40: =SUMIF($D$17:$D$33,E40,$I$17:$I$33) | G40: =IFERROR(F40/$I$34,0)
A41: • | B41: Custo por saca | C41: =IFERROR(I34/J13,0) | E41: TOTAL | F41: =SUM(F37:F40) | G41: =IFERROR(F41/$I$34,0)
A42: • | B42: Receita estimada | C42: =L13
A43: • | B43: Resultado estimado | C43: =L13-I34
A44: • | B44: Ponto de equilíbrio (sc/ha) | C44: =IFERROR(C39/B6,0)
A45: • | B45: Conferência: total talhões − lançamentos | C45: =ROUND(H13-I34,2)
