Workbook

Sheet Como usar
A1: Gestão de Rebanho Bovino
A2: Coleção Gestão no Campo • Instruções de uso
B4: Legenda de cores:
B5: Amarelo claro | C5: Células para você preencher (digitação livre ou lista suspensa).
B6: Cinza claro | C6: Fórmulas automáticas. Ficam protegidas para evitar que sejam apagadas por engano.
B7: Verde claro | C7: Linhas de total e resultados principais.
B9: Passo a passo
B10: Passo 1 | C10: Aba Config: confira a data de referência (por padrão, a data de hoje), o ano de análise e as faixas de idade das categorias. Você pode ajustar as idades e os nomes das categorias ao padrão da sua fazenda.
B11: Passo 2 | C11: Aba Animais: cadastre cada animal com brinco (único), sexo (M/F), data de nascimento, data e peso de entrada (nascimento ou compra). Idade, categoria, status, último peso e GMD são calculados.
B12: Passo 3 | C12: Categoria manual (opcional): use para animais cuja categoria não depende só da idade, como Touro ou animais de descarte. Ela substitui a categoria automática.
B13: Passo 4 | C13: Aba Pesagens: a cada pesagem, registre data, brinco e peso. A planilha busca a pesagem anterior do mesmo animal e calcula o GMD (ganho médio diário) do período.
B14: Passo 5 | C14: Aba Movimentações: registre nascimentos, compras, vendas e mortes. Animais com Venda ou Morte passam automaticamente para o status 'Vendido' ou 'Morto' e saem do inventário.
B15: Passo 6 | C15: Abas Inventário e Painel: veja o rebanho ativo por categoria, peso médio, GMD médio e o resumo das movimentações do ano.
B17: Como os cálculos funcionam
B18: • | C18: Idade (meses) = meses completos entre o nascimento e a data de referência da aba Config.
B19: • | C19: Categoria automática: definida pelo sexo e pela idade, conforme a tabela de faixas da aba Config.
B20: • | C20: GMD da pesagem = (peso atual − peso da pesagem anterior) ÷ dias entre as duas pesagens.
B21: • | C21: GMD desde a entrada (aba Animais) = (último peso − peso de entrada) ÷ dias entre a data de entrada e a última pesagem.
B23: Dicas
B24: • | C24: Cadastre o animal na aba Animais antes de lançar pesagens ou movimentações — os brincos aparecem na lista suspensa.
B25: • | C25: Não repita brincos: a planilha avisa se o brinco já existir.
B26: • | C26: Para ver o rebanho em uma data passada, altere a data de referência na Config.
B27: • | C27: Capacidade: 1.000 animais, 2.000 pesagens e 1.500 movimentações.
B29: Proteção das planilhas
C30: As abas estão protegidas SEM SENHA apenas para evitar exclusão acidental de fórmulas. Para personalizar: Excel → guia Revisão → Desproteger Planilha (no LibreOffice: Ferramentas → Proteger planilha; no Google Planilhas a proteção não é importada). Lembre-se de proteger novamente depois.
C32: Compatível com Microsoft Excel 2010 ou superior, LibreOffice Calc e Google Planilhas. A aba 'Exemplo' contém apenas dados FICTÍCIOS para demonstração e pode ser excluída.

Sheet Painel
A1: Painel do Rebanho
A2: Resumo do rebanho ativo e das movimentações do ano
B4: ="Propriedade: "&IF(Config!B6="","(informe na aba Config)",Config!B6)&" • Referência: "&RIGHT("0"&DAY(Config!B5),2)&"/"&RIGHT("0"&MONTH(Config!B5),2)&"/"&YEAR(Config!B5)&" • Ano de análise: "&Config!B7
B5: Indicadores | E5: Rebanho ativo por categoria | H5: Movimentações no ano
B6: Total de cabeças ativas | C6: ='Inventário'!B20 | E6: Categoria | F6: Cabeças | H6: Tipo | I6: Cabeças
B7: Machos ativos | C7: =COUNTIFS('Animais'!$C$6:$C$1005,"M",'Animais'!$N$6:$N$1005,"Ativo") | E7: ='Inventário'!A7 | F7: =IF(E7="","",'Inventário'!B7) | H7: ='Inventário'!A26 | I7: ='Inventário'!B26
B8: Fêmeas ativas | C8: =COUNTIFS('Animais'!$C$6:$C$1005,"F",'Animais'!$N$6:$N$1005,"Ativo") | E8: ='Inventário'!A8 | F8: =IF(E8="","",'Inventário'!B8) | H8: ='Inventário'!A27 | I8: ='Inventário'!B27
B9: Peso médio do rebanho ativo (kg) | C9: ='Inventário'!D20 | E9: ='Inventário'!A9 | F9: =IF(E9="","",'Inventário'!B9) | H9: ='Inventário'!A28 | I9: ='Inventário'!B28
B10: Peso vivo total do rebanho ativo (kg) | C10: ='Inventário'!E20 | E10: ='Inventário'!A10 | F10: =IF(E10="","",'Inventário'!B10) | H10: ='Inventário'!A29 | I10: ='Inventário'!B29
B11: GMD médio desde a entrada (kg/dia) | C11: ='Inventário'!F20 | E11: ='Inventário'!A11 | F11: =IF(E11="","",'Inventário'!B11)
B12: Nascimentos no ano | C12: ='Inventário'!B26 | E12: ='Inventário'!A12 | F12: =IF(E12="","",'Inventário'!B12)
B13: Compras no ano (cabeças) | C13: ='Inventário'!B27 | E13: ='Inventário'!A13 | F13: =IF(E13="","",'Inventário'!B13)
B14: Vendas no ano (cabeças) | C14: ='Inventário'!B28 | E14: ='Inventário'!A14 | F14: =IF(E14="","",'Inventário'!B14)
B15: Mortes no ano (cabeças) | C15: ='Inventário'!B29 | E15: ='Inventário'!A15 | F15: =IF(E15="","",'Inventário'!B15)
B16: Valor das compras no ano | C16: ='Inventário'!C27 | E16: ='Inventário'!A16 | F16: =IF(E16="","",'Inventário'!B16)
B17: Valor das vendas no ano | C17: ='Inventário'!C28 | E17: ='Inventário'!A17 | F17: =IF(E17="","",'Inventário'!B17)
B18: Ativos sem pesagem nos últimos 90 dias | C18: =COUNTIFS('Animais'!$N$6:$N$1005,"Ativo")-COUNTIFS('Animais'!$N$6:$N$1005,"Ativo",'Animais'!$O$6:$O$1005,">="&(Config!B5-90)) | E18: ='Inventário'!A18 | F18: =IF(E18="","",'Inventário'!B18)
E19: ='Inventário'!A19 | F19: =IF(E19="","",'Inventário'!B19)
E20: TOTAL | F20: =SUM(F7:F19)

Sheet Config
A1: Configurações
A2: Data de referência e faixas de idade das categorias
A3: Legenda: | B3: Preencher | C3: Cálculo automático (protegido)
A4: Dados gerais
A5: Data de referência (idade e inventário) | B5: =TODAY()
A6: Nome da propriedade
A7: Ano de análise das movimentações | B7: =YEAR(B5)
A9: Faixas de idade das categorias automáticas
A10: A partir de (meses de idade) | B10: Categoria — Macho | C10: Categoria — Fêmea
A11: 0 | B11: Bezerro | C11: Bezerra
A12: 12 | B12: Garrote | C12: Novilha 1-2 anos
A13: 24 | B13: Novilho | C13: Novilha 2-3 anos
A14: 36 | B14: Boi | C14: Vaca
A16: Categorias manuais (Touro, descarte etc.)
A17: Categoria manual
A18: Touro
A19: Vaca de descarte
A20: Boi de descarte
A24: As idades devem ser crescentes. A primeira faixa sempre começa em 0 mês.

Sheet Animais
A1: Cadastro de Animais
A2: Um animal por linha — categoria, status, último peso e GMD automáticos
A3: Legenda: | B3: Preencher | C3: Cálculo automático (protegido)
A5: Brinco | B5: Nome / apelido | C5: Sexo (M/F) | D5: Data de nascimento | E5: Raça | F5: Lote / pasto | G5: Origem | H5: Brinco da mãe | I5: Data de entrada | J5: Peso de entrada (kg) | K5: Categoria manual (opcional) | L5: Idade (meses) | M5: Categoria | N5: Status | O5: Data da última pesagem | P5: Último peso (kg) | Q5: GMD desde a entrada (kg/dia)
L6: =IF(OR(A6="",D6=""),"",IF(D6>Config!$B$5,0,DATEDIF(D6,Config!$B$5,"m"))) | M6: =IF(A6="","",IF(K6<>"",K6,IF(OR(C6="",D6=""),"Sem dados",IFERROR(IF(C6="M",INDEX(Config!$B$11:$B$14,MATCH(L6,Config!$A$11:$A$14,1)),IF(C6="F",INDEX(Config!$C$11:$C$14,MATCH(L6,Config!$A$11:$A$14,1)),"Sem dados")),"Verificar")))) | N6: =IF(A6="","",IF(COUNTIFS('Movimentações'!$C$6:$C$1505,A6,'Movimentações'!$B$6:$B$1505,"Venda")>0,"Vendido",IF(COUNTIFS('Movimentações'!$C$6:$C$1505,A6,'Movimentações'!$B$6:$B$1505,"Morte")>0,"Morto","Ativo"))) | O6: =IF(A6="","",IF(COUNTIF('Pesagens'!$B$6:$B$2005,A6)=0,"",SUMPRODUCT(MAX(('Pesagens'!$B$6:$B$2005=A6)*'Pesagens'!$A$6:$A$2005)))) | P6: =IF(A6="","",IF(O6="",IF(J6="","",J6),IFERROR(AVERAGEIFS('Pesagens'!$C$6:$C$2005,'Pesagens'!$B$6:$B$2005,A6,'Pesagens'!$A$6:$A$2005,O6),""))) | Q6: =IF(OR(A6="",O6="",I6="",J6=""),"",IFERROR((P6-J6)/(O6-I6),""))
L7: =IF(OR(A7="",D7=""),"",IF(D7>Config!$B$5,0,DATEDIF(D7,Config!$B$5,"m"))) | M7: =IF(A7="","",IF(K7<>"",K7,IF(OR(C7="",D7=""),"Sem dados",IFERROR(IF(C7="M",INDEX(Config!$B$11:$B$14,MATCH(L7,Config!$A$11:$A$14,1)),IF(C7="F",INDEX(Config!$C$11:$C$14,MATCH(L7,Config!$A$11:$A$14,1)),"Sem dados")),"Verificar")))) | N7: =IF(A7="","",IF(COUNTIFS('Movimentações'!$C$6:$C$1505,A7,'Movimentações'!$B$6:$B$1505,"Venda")>0,"Vendido",IF(COUNTIFS('Movimentações'!$C$6:$C$1505,A7,'Movimentações'!$B$6:$B$1505,"Morte")>0,"Morto","Ativo"))) | O7: =IF(A7="","",IF(COUNTIF('Pesagens'!$B$6:$B$2005,A7)=0,"",SUMPRODUCT(MAX(('Pesagens'!$B$6:$B$2005=A7)*'Pesagens'!$A$6:$A$2005)))) | P7: =IF(A7="","",IF(O7="",IF(J7="","",J7),IFERROR(AVERAGEIFS('Pesagens'!$C$6:$C$2005,'Pesagens'!$B$6:$B$2005,A7,'Pesagens'!$A$6:$A$2005,O7),""))) | Q7: =IF(OR(A7="",O7="",I7="",J7=""),"",IFERROR((P7-J7)/(O7-I7),""))
L8: =IF(OR(A8="",D8=""),"",IF(D8>Config!$B$5,0,DATEDIF(D8,Config!$B$5,"m"))) | M8: =IF(A8="","",IF(K8<>"",K8,IF(OR(C8="",D8=""),"Sem dados",IFERROR(IF(C8="M",INDEX(Config!$B$11:$B$14,MATCH(L8,Config!$A$11:$A$14,1)),IF(C8="F",INDEX(Config!$C$11:$C$14,MATCH(L8,Config!$A$11:$A$14,1)),"Sem dados")),"Verificar")))) | N8: =IF(A8="","",IF(COUNTIFS('Movimentações'!$C$6:$C$1505,A8,'Movimentações'!$B$6:$B$1505,"Venda")>0,"Vendido",IF(COUNTIFS('Movimentações'!$C$6:$C$1505,A8,'Movimentações'!$B$6:$B$1505,"Morte")>0,"Morto","Ativo"))) | O8: =IF(A8="","",IF(COUNTIF('Pesagens'!$B$6:$B$2005,A8)=0,"",SUMPRODUCT(MAX(('Pesagens'!$B$6:$B$2005=A8)*'Pesagens'!$A$6:$A$2005)))) | P8: =IF(A8="","",IF(O8="",IF(J8="","",J8),IFERROR(AVERAGEIFS('Pesagens'!$C$6:$C$2005,'Pesagens'!$B$6:$B$2005,A8,'Pesagens'!$A$6:$A$2005,O8),""))) | Q8: =IF(OR(A8="",O8="",I8="",J8=""),"",IFERROR((P8-J8)/(O8-I8),""))
L9: =IF(OR(A9="",D9=""),"",IF(D9>Config!$B$5,0,DATEDIF(D9,Config!$B$5,"m"))) | M9: =IF(A9="","",IF(K9<>"",K9,IF(OR(C9="",D9=""),"Sem dados",IFERROR(IF(C9="M",INDEX(Config!$B$11:$B$14,MATCH(L9,Config!$A$11:$A$14,1)),IF(C9="F",INDEX(Config!$C$11:$C$14,MATCH(L9,Config!$A$11:$A$14,1)),"Sem dados")),"Verificar")))) | N9: =IF(A9="","",IF(COUNTIFS('Movimentações'!$C$6:$C$1505,A9,'Movimentações'!$B$6:$B$1505,"Venda")>0,"Vendido",IF(COUNTIFS('Movimentações'!$C$6:$C$1505,A9,'Movimentações'!$B$6:$B$1505,"Morte")>0,"Morto","Ativo"))) | O9: =IF(A9="","",IF(COUNTIF('Pesagens'!$B$6:$B$2005,A9)=0,"",SUMPRODUCT(MAX(('Pesagens'!$B$6:$B$2005=A9)*'Pesagens'!$A$6:$A$2005)))) | P9: =IF(A9="","",IF(O9="",IF(J9="","",J9),IFERROR(AVERAGEIFS('Pesagens'!$C$6:$C$2005,'Pesagens'!$B$6:$B$2005,A9,'Pesagens'!$A$6:$A$2005,O9),""))) | Q9: =IF(OR(A9="",O9="",I9="",J9=""),"",IFERROR((P9-J9)/(O9-I9),""))
L10: =IF(OR(A10="",D10=""),"",IF(D10>Config!$B$5,0,DATEDIF(D10,Config!$B$5,"m"))) | M10: =IF(A10="","",IF(K10<>"",K10,IF(OR(C10="",D10=""),"Sem dados",IFERROR(IF(C10="M",INDEX(Config!$B$11:$B$14,MATCH(L10,Config!$A$11:$A$14,1)),IF(C10="F",INDEX(Config!$C$11:$C$14,MATCH(L10,Config!$A$11:$A$14,1)),"Sem dados")),"Verificar")))) | N10: =IF(A10="","",IF(COUNTIFS('Movimentações'!$C$6:$C$1505,A10,'Movimentações'!$B$6:$B$1505,"Venda")>0,"Vendido",IF(COUNTIFS('Movimentações'!$C$6:$C$1505,A10,'Movimentações'!$B$6:$B$1505,"Morte")>0,"Morto","Ativo"))) | O10: =IF(A10="","",IF(COUNTIF('Pesagens'!$B$6:$B$2005,A10)=0,"",SUMPRODUCT(MAX(('Pesagens'!$B$6:$B$2005=A10)*'Pesagens'!$A$6:$A$2005)))) | P10: =IF(A10="","",IF(O10="",IF(J10="","",J10),IFERROR(AVERAGEIFS('Pesagens'!$C$6:$C$2005,'Pesagens'!$B$6:$B$2005,A10,'Pesagens'!$A$6:$A$2005,O10),""))) | Q10: =IF(OR(A10="",O10="",I10="",J10=""),"",IFERROR((P10-J10)/(O10-I10),""))
L11: =IF(OR(A11="",D11=""),"",IF(D11>Config!$B$5,0,DATEDIF(D11,Config!$B$5,"m"))) | M11: =IF(A11="","",IF(K11<>"",K11,IF(OR(C11="",D11=""),"Sem dados",IFERROR(IF(C11="M",INDEX(Config!$B$11:$B$14,MATCH(L11,Config!$A$11:$A$14,1)),IF(C11="F",INDEX(Config!$C$11:$C$14,MATCH(L11,Config!$A$11:$A$14,1)),"Sem dados")),"Verificar")))) | N11: =IF(A11="","",IF(COUNTIFS('Movimentações'!$C$6:$C$1505,A11,'Movimentações'!$B$6:$B$1505,"Venda")>0,"Vendido",IF(COUNTIFS('Movimentações'!$C$6:$C$1505,A11,'Movimentações'!$B$6:$B$1505,"Morte")>0,"Morto","Ativo"))) | O11: =IF(A11="","",IF(COUNTIF('Pesagens'!$B$6:$B$2005,A11)=0,"",SUMPRODUCT(MAX(('Pesagens'!$B$6:$B$2005=A11)*'Pesagens'!$A$6:$A$2005)))) | P11: =IF(A11="","",IF(O11="",IF(J11="","",J11),IFERROR(AVERAGEIFS('Pesagens'!$C$6:$C$2005,'Pesagens'!$B$6:$B$2005,A11,'Pesagens'!$A$6:$A$2005,O11),""))) | Q11: =IF(OR(A11="",O11="",I11="",J11=""),"",IFERROR((P11-J11)/(O11-I11),""))
L12: =IF(OR(A12="",D12=""),"",IF(D12>Config!$B$5,0,DATEDIF(D12,Config!$B$5,"m"))) | M12: =IF(A12="","",IF(K12<>"",K12,IF(OR(C12="",D12=""),"Sem dados",IFERROR(IF(C12="M",INDEX(Config!$B$11:$B$14,MATCH(L12,Config!$A$11:$A$14,1)),IF(C12="F",INDEX(Config!$C$11:$C$14,MATCH(L12,Config!$A$11:$A$14,1)),"Sem dados")),"Verificar")))) | N12: =IF(A12="","",IF(COUNTIFS('Movimentações'!$C$6:$C$1505,A12,'Movimentações'!$B$6:$B$1505,"Venda")>0,"Vendido",IF(COUNTIFS('Movimentações'!$C$6:$C$1505,A12,'Movimentações'!$B$6:$B$1505,"Morte")>0,"Morto","Ativo"))) | O12: =IF(A12="","",IF(COUNTIF('Pesagens'!$B$6:$B$2005,A12)=0,"",SUMPRODUCT(MAX(('Pesagens'!$B$6:$B$2005=A12)*'Pesagens'!$A$6:$A$2005)))) | P12: =IF(A12="","",IF(O12="",IF(J12="","",J12),IFERROR(AVERAGEIFS('Pesagens'!$C$6:$C$2005,'Pesagens'!$B$6:$B$2005,A12,'Pesagens'!$A$6:$A$2005,O12),""))) | Q12: =IF(OR(A12="",O12="",I12="",J12=""),"",IFERROR((P12-J12)/(O12-I12),""))
L13: =IF(OR(A13="",D13=""),"",IF(D13>Config!$B$5,0,DATEDIF(D13,Config!$B$5,"m"))) | M13: =IF(A13="","",IF(K13<>"",K13,IF(OR(C13="",D13=""),"Sem dados",IFERROR(IF(C13="M",INDEX(Config!$B$11:$B$14,MATCH(L13,Config!$A$11:$A$14,1)),IF(C13="F",INDEX(Config!$C$11:$C$14,MATCH(L13,Config!$A$11:$A$14,1)),"Sem dados")),"Verificar")))) | N13: =IF(A13="","",IF(COUNTIFS('Movimentações'!$C$6:$C$1505,A13,'Movimentações'!$B$6:$B$1505,"Venda")>0,"Vendido",IF(COUNTIFS('Movimentações'!$C$6:$C$1505,A13,'Movimentações'!$B$6:$B$1505,"Morte")>0,"Morto","Ativo"))) | O13: =IF(A13="","",IF(COUNTIF('Pesagens'!$B$6:$B$2005,A13)=0,"",SUMPRODUCT(MAX(('Pesagens'!$B$6:$B$2005=A13)*'Pesagens'!$A$6:$A$2005)))) | P13: =IF(A13="","",IF(O13="",IF(J13="","",J13),IFERROR(AVERAGEIFS('Pesagens'!$C$6:$C$2005,'Pesagens'!$B$6:$B$2005,A13,'Pesagens'!$A$6:$A$2005,O13),""))) | Q13: =IF(OR(A13="",O13="",I13="",J13=""),"",IFERROR((P13-J13)/(O13-I13),""))
L14: =IF(OR(A14="",D14=""),"",IF(D14>Config!$B$5,0,DATEDIF(D14,Config!$B$5,"m"))) | M14: =IF(A14="","",IF(K14<>"",K14,IF(OR(C14="",D14=""),"Sem dados",IFERROR(IF(C14="M",INDEX(Config!$B$11:$B$14,MATCH(L14,Config!$A$11:$A$14,1)),IF(C14="F",INDEX(Config!$C$11:$C$14,MATCH(L14,Config!$A$11:$A$14,1)),"Sem dados")),"Verificar")))) | N14: =IF(A14="","",IF(COUNTIFS('Movimentações'!$C$6:$C$1505,A14,'Movimentações'!$B$6:$B$1505,"Venda")>0,"Vendido",IF(COUNTIFS('Movimentações'!$C$6:$C$1505,A14,'Movimentações'!$B$6:$B$1505,"Morte")>0,"Morto","Ativo"))) | O14: =IF(A14="","",IF(COUNTIF('Pesagens'!$B$6:$B$2005,A14)=0,"",SUMPRODUCT(MAX(('Pesagens'!$B$6:$B$2005=A14)*'Pesagens'!$A$6:$A$2005)))) | P14: =IF(A14="","",IF(O14="",IF(J14="","",J14),IFERROR(AVERAGEIFS('Pesagens'!$C$6:$C$2005,'Pesagens'!$B$6:$B$2005,A14,'Pesagens'!$A$6:$A$2005,O14),""))) | Q14: =IF(OR(A14="",O14="",I14="",J14=""),"",IFERROR((P14-J14)/(O14-I14),""))
L15: =IF(OR(A15="",D15=""),"",IF(D15>Config!$B$5,0,DATEDIF(D15,Config!$B$5,"m"))) | M15: =IF(A15="","",IF(K15<>"",K15,IF(OR(C15="",D15=""),"Sem dados",IFERROR(IF(C15="M",INDEX(Config!$B$11:$B$14,MATCH(L15,Config!$A$11:$A$14,1)),IF(C15="F",INDEX(Config!$C$11:$C$14,MATCH(L15,Config!$A$11:$A$14,1)),"Sem dados")),"Verificar")))) | N15: =IF(A15="","",IF(COUNTIFS('Movimentações'!$C$6:$C$1505,A15,'Movimentações'!$B$6:$B$1505,"Venda")>0,"Vendido",IF(COUNTIFS('Movimentações'!$C$6:$C$1505,A15,'Movimentações'!$B$6:$B$1505,"Morte")>0,"Morto","Ativo"))) | O15: =IF(A15="","",IF(COUNTIF('Pesagens'!$B$6:$B$2005,A15)=0,"",SUMPRODUCT(MAX(('Pesagens'!$B$6:$B$2005=A15)*'Pesagens'!$A$6:$A$2005)))) | P15: =IF(A15="","",IF(O15="",IF(J15="","",J15),IFERROR(AVERAGEIFS('Pesagens'!$C$6:$C$2005,'Pesagens'!$B$6:$B$2005,A15,'Pesagens'!$A$6:$A$2005,O15),""))) | Q15: =IF(OR(A15="",O15="",I15="",J15=""),"",IFERROR((P15-J15)/(O15-I15),""))
L16: =IF(OR(A16="",D16=""),"",IF(D16>Config!$B$5,0,DATEDIF(D16,Config!$B$5,"m"))) | M16: =IF(A16="","",IF(K16<>"",K16,IF(OR(C16="",D16=""),"Sem dados",IFERROR(IF(C16="M",INDEX(Config!$B$11:$B$14,MATCH(L16,Config!$A$11:$A$14,1)),IF(C16="F",INDEX(Config!$C$11:$C$14,MATCH(L16,Config!$A$11:$A$14,1)),"Sem dados")),"Verificar")))) | N16: =IF(A16="","",IF(COUNTIFS('Movimentações'!$C$6:$C$1505,A16,'Movimentações'!$B$6:$B$1505,"Venda")>0,"Vendido",IF(COUNTIFS('Movimentações'!$C$6:$C$1505,A16,'Movimentações'!$B$6:$B$1505,"Morte")>0,"Morto","Ativo"))) | O16: =IF(A16="","",IF(COUNTIF('Pesagens'!$B$6:$B$2005,A16)=0,"",SUMPRODUCT(MAX(('Pesagens'!$B$6:$B$2005=A16)*'Pesagens'!$A$6:$A$2005)))) | P16: =IF(A16="","",IF(O16="",IF(J16="","",J16),IFERROR(AVERAGEIFS('Pesagens'!$C$6:$C$2005,'Pesagens'!$B$6:$B$2005,A16,'Pesagens'!$A$6:$A$2005,O16),""))) | Q16: =IF(OR(A16="",O16="",I16="",J16=""),"",IFERROR((P16-J16)/(O16-I16),""))
L17: =IF(OR(A17="",D17=""),"",IF(D17>Config!$B$5,0,DATEDIF(D17,Config!$B$5,"m"))) | M17: =IF(A17="","",IF(K17<>"",K17,IF(OR(C17="",D17=""),"Sem dados",IFERROR(IF(C17="M",INDEX(Config!$B$11:$B$14,MATCH(L17,Config!$A$11:$A$14,1)),IF(C17="F",INDEX(Config!$C$11:$C$14,MATCH(L17,Config!$A$11:$A$14,1)),"Sem dados")),"Verificar")))) | N17: =IF(A17="","",IF(COUNTIFS('Movimentações'!$C$6:$C$1505,A17,'Movimentações'!$B$6:$B$1505,"Venda")>0,"Vendido",IF(COUNTIFS('Movimentações'!$C$6:$C$1505,A17,'Movimentações'!$B$6:$B$1505,"Morte")>0,"Morto","Ativo"))) | O17: =IF(A17="","",IF(COUNTIF('Pesagens'!$B$6:$B$2005,A17)=0,"",SUMPRODUCT(MAX(('Pesagens'!$B$6:$B$2005=A17)*'Pesagens'!$A$6:$A$2005)))) | P17: =IF(A17="","",IF(O17="",IF(J17="","",J17),IFERROR(AVERAGEIFS('Pesagens'!$C$6:$C$2005,'Pesagens'!$B$6:$B$2005,A17,'Pesagens'!$A$6:$A$2005,O17),""))) | Q17: =IF(OR(A17="",O17="",I17="",J17=""),"",IFERROR((P17-J17)/(O17-I17),""))
... L1005: =IF(OR(A1005="",D1005=""),"",IF(D1005>Config!$B$5,0,DATEDIF(D1005,Config!$B$5,"m"))) | M1005: =IF(A1005="","",IF(K1005<>"",K1005,IF(OR(C1005="",D1005=""),"Sem dados",IFERROR(IF(C1005="M",INDEX(Config!$B$11:$B$14,MATCH(L1005,Config!$A$11:$A$14,1)),IF(C1005="F",INDEX(Config!$C$11:$C$14,MATCH(L1005,Config!$A$11:$A$14,1)),"Sem dados")),"Verificar")))) | N1005: =IF(A1005="","",IF(COUNTIFS('Movimentações'!$C$6:$C$1505,A1005,'Movimentações'!$B$6:$B$1505,"Venda")>0,"Vendido",IF(COUNTIFS('Movimentações'!$C$6:$C$1505,A1005,'Movimentações'!$B$6:$B$1505,"Morte")>0,"Morto","Ativo"))) | O1005: =IF(A1005="","",IF(COUNTIF('Pesagens'!$B$6:$B$2005,A1005)=0,"",SUMPRODUCT(MAX(('Pesagens'!$B$6:$B$2005=A1005)*'Pesagens'!$A$6:$A$2005)))) | P1005: =IF(A1005="","",IF(O1005="",IF(J1005="","",J1005),IFERROR(AVERAGEIFS('Pesagens'!$C$6:$C$2005,'Pesagens'!$B$6:$B$2005,A1005,'Pesagens'!$A$6:$A$2005,O1005),""))) | Q1005: =IF(OR(A1005="",O1005="",I1005="",J1005=""),"",IFERROR((P1005-J1005)/(O1005-I1005),""))

Sheet Pesagens
A1: Pesagens
A2: O GMD é calculado em relação à pesagem anterior do mesmo animal
A3: Legenda: | B3: Preencher | C3: Cálculo automático (protegido)
A5: Data da pesagem | B5: Brinco | C5: Peso (kg) | D5: Observação | E5: Pesagem anterior (data) | F5: Peso anterior (kg) | G5: Dias no período | H5: GMD do período (kg/dia) | I5: Categoria atual
E6: =IF(OR(A6="",B6=""),"",SUMPRODUCT(MAX(($B$6:$B$2005=B6)*($A$6:$A$2005<A6)*$A$6:$A$2005))) | F6: =IF(OR(E6="",E6=0),"",IFERROR(AVERAGEIFS($C$6:$C$2005,$B$6:$B$2005,B6,$A$6:$A$2005,E6),"")) | G6: =IF(F6="","",A6-E6) | H6: =IF(OR(F6="",C6=""),"",IFERROR((C6-F6)/G6,"")) | I6: =IF(B6="","",IFERROR(INDEX('Animais'!$M$6:$M$1005,MATCH(B6,'Animais'!$A$6:$A$1005,0)),"Brinco não cadastrado"))
E7: =IF(OR(A7="",B7=""),"",SUMPRODUCT(MAX(($B$6:$B$2005=B7)*($A$6:$A$2005<A7)*$A$6:$A$2005))) | F7: =IF(OR(E7="",E7=0),"",IFERROR(AVERAGEIFS($C$6:$C$2005,$B$6:$B$2005,B7,$A$6:$A$2005,E7),"")) | G7: =IF(F7="","",A7-E7) | H7: =IF(OR(F7="",C7=""),"",IFERROR((C7-F7)/G7,"")) | I7: =IF(B7="","",IFERROR(INDEX('Animais'!$M$6:$M$1005,MATCH(B7,'Animais'!$A$6:$A$1005,0)),"Brinco não cadastrado"))
E8: =IF(OR(A8="",B8=""),"",SUMPRODUCT(MAX(($B$6:$B$2005=B8)*($A$6:$A$2005<A8)*$A$6:$A$2005))) | F8: =IF(OR(E8="",E8=0),"",IFERROR(AVERAGEIFS($C$6:$C$2005,$B$6:$B$2005,B8,$A$6:$A$2005,E8),"")) | G8: =IF(F8="","",A8-E8) | H8: =IF(OR(F8="",C8=""),"",IFERROR((C8-F8)/G8,"")) | I8: =IF(B8="","",IFERROR(INDEX('Animais'!$M$6:$M$1005,MATCH(B8,'Animais'!$A$6:$A$1005,0)),"Brinco não cadastrado"))
E9: =IF(OR(A9="",B9=""),"",SUMPRODUCT(MAX(($B$6:$B$2005=B9)*($A$6:$A$2005<A9)*$A$6:$A$2005))) | F9: =IF(OR(E9="",E9=0),"",IFERROR(AVERAGEIFS($C$6:$C$2005,$B$6:$B$2005,B9,$A$6:$A$2005,E9),"")) | G9: =IF(F9="","",A9-E9) | H9: =IF(OR(F9="",C9=""),"",IFERROR((C9-F9)/G9,"")) | I9: =IF(B9="","",IFERROR(INDEX('Animais'!$M$6:$M$1005,MATCH(B9,'Animais'!$A$6:$A$1005,0)),"Brinco não cadastrado"))
E10: =IF(OR(A10="",B10=""),"",SUMPRODUCT(MAX(($B$6:$B$2005=B10)*($A$6:$A$2005<A10)*$A$6:$A$2005))) | F10: =IF(OR(E10="",E10=0),"",IFERROR(AVERAGEIFS($C$6:$C$2005,$B$6:$B$2005,B10,$A$6:$A$2005,E10),"")) | G10: =IF(F10="","",A10-E10) | H10: =IF(OR(F10="",C10=""),"",IFERROR((C10-F10)/G10,"")) | I10: =IF(B10="","",IFERROR(INDEX('Animais'!$M$6:$M$1005,MATCH(B10,'Animais'!$A$6:$A$1005,0)),"Brinco não cadastrado"))
E11: =IF(OR(A11="",B11=""),"",SUMPRODUCT(MAX(($B$6:$B$2005=B11)*($A$6:$A$2005<A11)*$A$6:$A$2005))) | F11: =IF(OR(E11="",E11=0),"",IFERROR(AVERAGEIFS($C$6:$C$2005,$B$6:$B$2005,B11,$A$6:$A$2005,E11),"")) | G11: =IF(F11="","",A11-E11) | H11: =IF(OR(F11="",C11=""),"",IFERROR((C11-F11)/G11,"")) | I11: =IF(B11="","",IFERROR(INDEX('Animais'!$M$6:$M$1005,MATCH(B11,'Animais'!$A$6:$A$1005,0)),"Brinco não cadastrado"))
E12: =IF(OR(A12="",B12=""),"",SUMPRODUCT(MAX(($B$6:$B$2005=B12)*($A$6:$A$2005<A12)*$A$6:$A$2005))) | F12: =IF(OR(E12="",E12=0),"",IFERROR(AVERAGEIFS($C$6:$C$2005,$B$6:$B$2005,B12,$A$6:$A$2005,E12),"")) | G12: =IF(F12="","",A12-E12) | H12: =IF(OR(F12="",C12=""),"",IFERROR((C12-F12)/G12,"")) | I12: =IF(B12="","",IFERROR(INDEX('Animais'!$M$6:$M$1005,MATCH(B12,'Animais'!$A$6:$A$1005,0)),"Brinco não cadastrado"))
E13: =IF(OR(A13="",B13=""),"",SUMPRODUCT(MAX(($B$6:$B$2005=B13)*($A$6:$A$2005<A13)*$A$6:$A$2005))) | F13: =IF(OR(E13="",E13=0),"",IFERROR(AVERAGEIFS($C$6:$C$2005,$B$6:$B$2005,B13,$A$6:$A$2005,E13),"")) | G13: =IF(F13="","",A13-E13) | H13: =IF(OR(F13="",C13=""),"",IFERROR((C13-F13)/G13,"")) | I13: =IF(B13="","",IFERROR(INDEX('Animais'!$M$6:$M$1005,MATCH(B13,'Animais'!$A$6:$A$1005,0)),"Brinco não cadastrado"))
E14: =IF(OR(A14="",B14=""),"",SUMPRODUCT(MAX(($B$6:$B$2005=B14)*($A$6:$A$2005<A14)*$A$6:$A$2005))) | F14: =IF(OR(E14="",E14=0),"",IFERROR(AVERAGEIFS($C$6:$C$2005,$B$6:$B$2005,B14,$A$6:$A$2005,E14),"")) | G14: =IF(F14="","",A14-E14) | H14: =IF(OR(F14="",C14=""),"",IFERROR((C14-F14)/G14,"")) | I14: =IF(B14="","",IFERROR(INDEX('Animais'!$M$6:$M$1005,MATCH(B14,'Animais'!$A$6:$A$1005,0)),"Brinco não cadastrado"))
E15: =IF(OR(A15="",B15=""),"",SUMPRODUCT(MAX(($B$6:$B$2005=B15)*($A$6:$A$2005<A15)*$A$6:$A$2005))) | F15: =IF(OR(E15="",E15=0),"",IFERROR(AVERAGEIFS($C$6:$C$2005,$B$6:$B$2005,B15,$A$6:$A$2005,E15),"")) | G15: =IF(F15="","",A15-E15) | H15: =IF(OR(F15="",C15=""),"",IFERROR((C15-F15)/G15,"")) | I15: =IF(B15="","",IFERROR(INDEX('Animais'!$M$6:$M$1005,MATCH(B15,'Animais'!$A$6:$A$1005,0)),"Brinco não cadastrado"))
E16: =IF(OR(A16="",B16=""),"",SUMPRODUCT(MAX(($B$6:$B$2005=B16)*($A$6:$A$2005<A16)*$A$6:$A$2005))) | F16: =IF(OR(E16="",E16=0),"",IFERROR(AVERAGEIFS($C$6:$C$2005,$B$6:$B$2005,B16,$A$6:$A$2005,E16),"")) | G16: =IF(F16="","",A16-E16) | H16: =IF(OR(F16="",C16=""),"",IFERROR((C16-F16)/G16,"")) | I16: =IF(B16="","",IFERROR(INDEX('Animais'!$M$6:$M$1005,MATCH(B16,'Animais'!$A$6:$A$1005,0)),"Brinco não cadastrado"))
E17: =IF(OR(A17="",B17=""),"",SUMPRODUCT(MAX(($B$6:$B$2005=B17)*($A$6:$A$2005<A17)*$A$6:$A$2005))) | F17: =IF(OR(E17="",E17=0),"",IFERROR(AVERAGEIFS($C$6:$C$2005,$B$6:$B$2005,B17,$A$6:$A$2005,E17),"")) | G17: =IF(F17="","",A17-E17) | H17: =IF(OR(F17="",C17=""),"",IFERROR((C17-F17)/G17,"")) | I17: =IF(B17="","",IFERROR(INDEX('Animais'!$M$6:$M$1005,MATCH(B17,'Animais'!$A$6:$A$1005,0)),"Brinco não cadastrado"))
... E2005: =IF(OR(A2005="",B2005=""),"",SUMPRODUCT(MAX(($B$6:$B$2005=B2005)*($A$6:$A$2005<A2005)*$A$6:$A$2005))) | F2005: =IF(OR(E2005="",E2005=0),"",IFERROR(AVERAGEIFS($C$6:$C$2005,$B$6:$B$2005,B2005,$A$6:$A$2005,E2005),"")) | G2005: =IF(F2005="","",A2005-E2005) | H2005: =IF(OR(F2005="",C2005=""),"",IFERROR((C2005-F2005)/G2005,"")) | I2005: =IF(B2005="","",IFERROR(INDEX('Animais'!$M$6:$M$1005,MATCH(B2005,'Animais'!$A$6:$A$1005,0)),"Brinco não cadastrado"))

Sheet Movimentações
A1: Movimentações
A2: Nascimentos, compras, vendas e mortes
A3: Legenda: | B3: Preencher | C3: Cálculo automático (protegido)
A5: Data | B5: Tipo | C5: Brinco | D5: Peso (kg) | E5: Valor (R$) | F5: Comprador / fornecedor / causa | G5: Observação | H5: Categoria | I5: Ano | J5: R$ por kg
H6: =IF(C6="","",IFERROR(INDEX('Animais'!$M$6:$M$1005,MATCH(C6,'Animais'!$A$6:$A$1005,0)),"Brinco não cadastrado")) | I6: =IF(A6="","",YEAR(A6)) | J6: =IF(OR(N(D6)=0,N(E6)=0),"",IFERROR(E6/D6,""))
H7: =IF(C7="","",IFERROR(INDEX('Animais'!$M$6:$M$1005,MATCH(C7,'Animais'!$A$6:$A$1005,0)),"Brinco não cadastrado")) | I7: =IF(A7="","",YEAR(A7)) | J7: =IF(OR(N(D7)=0,N(E7)=0),"",IFERROR(E7/D7,""))
H8: =IF(C8="","",IFERROR(INDEX('Animais'!$M$6:$M$1005,MATCH(C8,'Animais'!$A$6:$A$1005,0)),"Brinco não cadastrado")) | I8: =IF(A8="","",YEAR(A8)) | J8: =IF(OR(N(D8)=0,N(E8)=0),"",IFERROR(E8/D8,""))
H9: =IF(C9="","",IFERROR(INDEX('Animais'!$M$6:$M$1005,MATCH(C9,'Animais'!$A$6:$A$1005,0)),"Brinco não cadastrado")) | I9: =IF(A9="","",YEAR(A9)) | J9: =IF(OR(N(D9)=0,N(E9)=0),"",IFERROR(E9/D9,""))
H10: =IF(C10="","",IFERROR(INDEX('Animais'!$M$6:$M$1005,MATCH(C10,'Animais'!$A$6:$A$1005,0)),"Brinco não cadastrado")) | I10: =IF(A10="","",YEAR(A10)) | J10: =IF(OR(N(D10)=0,N(E10)=0),"",IFERROR(E10/D10,""))
H11: =IF(C11="","",IFERROR(INDEX('Animais'!$M$6:$M$1005,MATCH(C11,'Animais'!$A$6:$A$1005,0)),"Brinco não cadastrado")) | I11: =IF(A11="","",YEAR(A11)) | J11: =IF(OR(N(D11)=0,N(E11)=0),"",IFERROR(E11/D11,""))
H12: =IF(C12="","",IFERROR(INDEX('Animais'!$M$6:$M$1005,MATCH(C12,'Animais'!$A$6:$A$1005,0)),"Brinco não cadastrado")) | I12: =IF(A12="","",YEAR(A12)) | J12: =IF(OR(N(D12)=0,N(E12)=0),"",IFERROR(E12/D12,""))
H13: =IF(C13="","",IFERROR(INDEX('Animais'!$M$6:$M$1005,MATCH(C13,'Animais'!$A$6:$A$1005,0)),"Brinco não cadastrado")) | I13: =IF(A13="","",YEAR(A13)) | J13: =IF(OR(N(D13)=0,N(E13)=0),"",IFERROR(E13/D13,""))
H14: =IF(C14="","",IFERROR(INDEX('Animais'!$M$6:$M$1005,MATCH(C14,'Animais'!$A$6:$A$1005,0)),"Brinco não cadastrado")) | I14: =IF(A14="","",YEAR(A14)) | J14: =IF(OR(N(D14)=0,N(E14)=0),"",IFERROR(E14/D14,""))
H15: =IF(C15="","",IFERROR(INDEX('Animais'!$M$6:$M$1005,MATCH(C15,'Animais'!$A$6:$A$1005,0)),"Brinco não cadastrado")) | I15: =IF(A15="","",YEAR(A15)) | J15: =IF(OR(N(D15)=0,N(E15)=0),"",IFERROR(E15/D15,""))
H16: =IF(C16="","",IFERROR(INDEX('Animais'!$M$6:$M$1005,MATCH(C16,'Animais'!$A$6:$A$1005,0)),"Brinco não cadastrado")) | I16: =IF(A16="","",YEAR(A16)) | J16: =IF(OR(N(D16)=0,N(E16)=0),"",IFERROR(E16/D16,""))
H17: =IF(C17="","",IFERROR(INDEX('Animais'!$M$6:$M$1005,MATCH(C17,'Animais'!$A$6:$A$1005,0)),"Brinco não cadastrado")) | I17: =IF(A17="","",YEAR(A17)) | J17: =IF(OR(N(D17)=0,N(E17)=0),"",IFERROR(E17/D17,""))
... H1505: =IF(C1505="","",IFERROR(INDEX('Animais'!$M$6:$M$1005,MATCH(C1505,'Animais'!$A$6:$A$1005,0)),"Brinco não cadastrado")) | I1505: =IF(A1505="","",YEAR(A1505)) | J1505: =IF(OR(N(D1505)=0,N(E1505)=0),"",IFERROR(E1505/D1505,""))

Sheet Listas
A1: Categorias
A2: =Config!B11
A3: =Config!B12
A4: =Config!B13
A5: =Config!B14
A6: =Config!C11
A7: =Config!C12
A8: =Config!C13
A9: =Config!C14
A10: =IF(Config!A18="","",Config!A18)
A11: =IF(Config!A19="","",Config!A19)
A12: =IF(Config!A20="","",Config!A20)
A13: =IF(Config!A21="","",Config!A21)
A14: =IF(Config!A22="","",Config!A22)

Sheet Inventário
A1: Inventário do Rebanho
A2: Somente animais com status 'Ativo' na data de referência
A3: Legenda: | B3: Preencher | C3: Cálculo automático (protegido)
A4: ="Data de referência: "&RIGHT("0"&DAY(Config!B5),2)&"/"&RIGHT("0"&MONTH(Config!B5),2)&"/"&YEAR(Config!B5)
A6: Categoria | B6: Cabeças ativas | C6: % do rebanho | D6: Peso médio (kg) | E6: Peso total (kg) | F6: GMD médio desde a entrada (kg/dia)
A7: =Listas!A2 | B7: =IF(A7="","",COUNTIFS('Animais'!$M$6:$M$1005,A7,'Animais'!$N$6:$N$1005,"Ativo")) | C7: =IF(A7="","",IFERROR(B7/$B$20,0)) | D7: =IF(A7="","",IFERROR(AVERAGEIFS('Animais'!$P$6:$P$1005,'Animais'!$M$6:$M$1005,A7,'Animais'!$N$6:$N$1005,"Ativo"),0)) | E7: =IF(A7="","",SUMIFS('Animais'!$P$6:$P$1005,'Animais'!$M$6:$M$1005,A7,'Animais'!$N$6:$N$1005,"Ativo")) | F7: =IF(A7="","",IFERROR(AVERAGEIFS('Animais'!$Q$6:$Q$1005,'Animais'!$M$6:$M$1005,A7,'Animais'!$N$6:$N$1005,"Ativo"),0))
A8: =Listas!A3 | B8: =IF(A8="","",COUNTIFS('Animais'!$M$6:$M$1005,A8,'Animais'!$N$6:$N$1005,"Ativo")) | C8: =IF(A8="","",IFERROR(B8/$B$20,0)) | D8: =IF(A8="","",IFERROR(AVERAGEIFS('Animais'!$P$6:$P$1005,'Animais'!$M$6:$M$1005,A8,'Animais'!$N$6:$N$1005,"Ativo"),0)) | E8: =IF(A8="","",SUMIFS('Animais'!$P$6:$P$1005,'Animais'!$M$6:$M$1005,A8,'Animais'!$N$6:$N$1005,"Ativo")) | F8: =IF(A8="","",IFERROR(AVERAGEIFS('Animais'!$Q$6:$Q$1005,'Animais'!$M$6:$M$1005,A8,'Animais'!$N$6:$N$1005,"Ativo"),0))
A9: =Listas!A4 | B9: =IF(A9="","",COUNTIFS('Animais'!$M$6:$M$1005,A9,'Animais'!$N$6:$N$1005,"Ativo")) | C9: =IF(A9="","",IFERROR(B9/$B$20,0)) | D9: =IF(A9="","",IFERROR(AVERAGEIFS('Animais'!$P$6:$P$1005,'Animais'!$M$6:$M$1005,A9,'Animais'!$N$6:$N$1005,"Ativo"),0)) | E9: =IF(A9="","",SUMIFS('Animais'!$P$6:$P$1005,'Animais'!$M$6:$M$1005,A9,'Animais'!$N$6:$N$1005,"Ativo")) | F9: =IF(A9="","",IFERROR(AVERAGEIFS('Animais'!$Q$6:$Q$1005,'Animais'!$M$6:$M$1005,A9,'Animais'!$N$6:$N$1005,"Ativo"),0))
A10: =Listas!A5 | B10: =IF(A10="","",COUNTIFS('Animais'!$M$6:$M$1005,A10,'Animais'!$N$6:$N$1005,"Ativo")) | C10: =IF(A10="","",IFERROR(B10/$B$20,0)) | D10: =IF(A10="","",IFERROR(AVERAGEIFS('Animais'!$P$6:$P$1005,'Animais'!$M$6:$M$1005,A10,'Animais'!$N$6:$N$1005,"Ativo"),0)) | E10: =IF(A10="","",SUMIFS('Animais'!$P$6:$P$1005,'Animais'!$M$6:$M$1005,A10,'Animais'!$N$6:$N$1005,"Ativo")) | F10: =IF(A10="","",IFERROR(AVERAGEIFS('Animais'!$Q$6:$Q$1005,'Animais'!$M$6:$M$1005,A10,'Animais'!$N$6:$N$1005,"Ativo"),0))
A11: =Listas!A6 | B11: =IF(A11="","",COUNTIFS('Animais'!$M$6:$M$1005,A11,'Animais'!$N$6:$N$1005,"Ativo")) | C11: =IF(A11="","",IFERROR(B11/$B$20,0)) | D11: =IF(A11="","",IFERROR(AVERAGEIFS('Animais'!$P$6:$P$1005,'Animais'!$M$6:$M$1005,A11,'Animais'!$N$6:$N$1005,"Ativo"),0)) | E11: =IF(A11="","",SUMIFS('Animais'!$P$6:$P$1005,'Animais'!$M$6:$M$1005,A11,'Animais'!$N$6:$N$1005,"Ativo")) | F11: =IF(A11="","",IFERROR(AVERAGEIFS('Animais'!$Q$6:$Q$1005,'Animais'!$M$6:$M$1005,A11,'Animais'!$N$6:$N$1005,"Ativo"),0))
A12: =Listas!A7 | B12: =IF(A12="","",COUNTIFS('Animais'!$M$6:$M$1005,A12,'Animais'!$N$6:$N$1005,"Ativo")) | C12: =IF(A12="","",IFERROR(B12/$B$20,0)) | D12: =IF(A12="","",IFERROR(AVERAGEIFS('Animais'!$P$6:$P$1005,'Animais'!$M$6:$M$1005,A12,'Animais'!$N$6:$N$1005,"Ativo"),0)) | E12: =IF(A12="","",SUMIFS('Animais'!$P$6:$P$1005,'Animais'!$M$6:$M$1005,A12,'Animais'!$N$6:$N$1005,"Ativo")) | F12: =IF(A12="","",IFERROR(AVERAGEIFS('Animais'!$Q$6:$Q$1005,'Animais'!$M$6:$M$1005,A12,'Animais'!$N$6:$N$1005,"Ativo"),0))
A13: =Listas!A8 | B13: =IF(A13="","",COUNTIFS('Animais'!$M$6:$M$1005,A13,'Animais'!$N$6:$N$1005,"Ativo")) | C13: =IF(A13="","",IFERROR(B13/$B$20,0)) | D13: =IF(A13="","",IFERROR(AVERAGEIFS('Animais'!$P$6:$P$1005,'Animais'!$M$6:$M$1005,A13,'Animais'!$N$6:$N$1005,"Ativo"),0)) | E13: =IF(A13="","",SUMIFS('Animais'!$P$6:$P$1005,'Animais'!$M$6:$M$1005,A13,'Animais'!$N$6:$N$1005,"Ativo")) | F13: =IF(A13="","",IFERROR(AVERAGEIFS('Animais'!$Q$6:$Q$1005,'Animais'!$M$6:$M$1005,A13,'Animais'!$N$6:$N$1005,"Ativo"),0))
A14: =Listas!A9 | B14: =IF(A14="","",COUNTIFS('Animais'!$M$6:$M$1005,A14,'Animais'!$N$6:$N$1005,"Ativo")) | C14: =IF(A14="","",IFERROR(B14/$B$20,0)) | D14: =IF(A14="","",IFERROR(AVERAGEIFS('Animais'!$P$6:$P$1005,'Animais'!$M$6:$M$1005,A14,'Animais'!$N$6:$N$1005,"Ativo"),0)) | E14: =IF(A14="","",SUMIFS('Animais'!$P$6:$P$1005,'Animais'!$M$6:$M$1005,A14,'Animais'!$N$6:$N$1005,"Ativo")) | F14: =IF(A14="","",IFERROR(AVERAGEIFS('Animais'!$Q$6:$Q$1005,'Animais'!$M$6:$M$1005,A14,'Animais'!$N$6:$N$1005,"Ativo"),0))
A15: =Listas!A10 | B15: =IF(A15="","",COUNTIFS('Animais'!$M$6:$M$1005,A15,'Animais'!$N$6:$N$1005,"Ativo")) | C15: =IF(A15="","",IFERROR(B15/$B$20,0)) | D15: =IF(A15="","",IFERROR(AVERAGEIFS('Animais'!$P$6:$P$1005,'Animais'!$M$6:$M$1005,A15,'Animais'!$N$6:$N$1005,"Ativo"),0)) | E15: =IF(A15="","",SUMIFS('Animais'!$P$6:$P$1005,'Animais'!$M$6:$M$1005,A15,'Animais'!$N$6:$N$1005,"Ativo")) | F15: =IF(A15="","",IFERROR(AVERAGEIFS('Animais'!$Q$6:$Q$1005,'Animais'!$M$6:$M$1005,A15,'Animais'!$N$6:$N$1005,"Ativo"),0))
A16: =Listas!A11 | B16: =IF(A16="","",COUNTIFS('Animais'!$M$6:$M$1005,A16,'Animais'!$N$6:$N$1005,"Ativo")) | C16: =IF(A16="","",IFERROR(B16/$B$20,0)) | D16: =IF(A16="","",IFERROR(AVERAGEIFS('Animais'!$P$6:$P$1005,'Animais'!$M$6:$M$1005,A16,'Animais'!$N$6:$N$1005,"Ativo"),0)) | E16: =IF(A16="","",SUMIFS('Animais'!$P$6:$P$1005,'Animais'!$M$6:$M$1005,A16,'Animais'!$N$6:$N$1005,"Ativo")) | F16: =IF(A16="","",IFERROR(AVERAGEIFS('Animais'!$Q$6:$Q$1005,'Animais'!$M$6:$M$1005,A16,'Animais'!$N$6:$N$1005,"Ativo"),0))
A17: =Listas!A12 | B17: =IF(A17="","",COUNTIFS('Animais'!$M$6:$M$1005,A17,'Animais'!$N$6:$N$1005,"Ativo")) | C17: =IF(A17="","",IFERROR(B17/$B$20,0)) | D17: =IF(A17="","",IFERROR(AVERAGEIFS('Animais'!$P$6:$P$1005,'Animais'!$M$6:$M$1005,A17,'Animais'!$N$6:$N$1005,"Ativo"),0)) | E17: =IF(A17="","",SUMIFS('Animais'!$P$6:$P$1005,'Animais'!$M$6:$M$1005,A17,'Animais'!$N$6:$N$1005,"Ativo")) | F17: =IF(A17="","",IFERROR(AVERAGEIFS('Animais'!$Q$6:$Q$1005,'Animais'!$M$6:$M$1005,A17,'Animais'!$N$6:$N$1005,"Ativo"),0))
A18: =Listas!A13 | B18: =IF(A18="","",COUNTIFS('Animais'!$M$6:$M$1005,A18,'Animais'!$N$6:$N$1005,"Ativo")) | C18: =IF(A18="","",IFERROR(B18/$B$20,0)) | D18: =IF(A18="","",IFERROR(AVERAGEIFS('Animais'!$P$6:$P$1005,'Animais'!$M$6:$M$1005,A18,'Animais'!$N$6:$N$1005,"Ativo"),0)) | E18: =IF(A18="","",SUMIFS('Animais'!$P$6:$P$1005,'Animais'!$M$6:$M$1005,A18,'Animais'!$N$6:$N$1005,"Ativo")) | F18: =IF(A18="","",IFERROR(AVERAGEIFS('Animais'!$Q$6:$Q$1005,'Animais'!$M$6:$M$1005,A18,'Animais'!$N$6:$N$1005,"Ativo"),0))
A19: =Listas!A14 | B19: =IF(A19="","",COUNTIFS('Animais'!$M$6:$M$1005,A19,'Animais'!$N$6:$N$1005,"Ativo")) | C19: =IF(A19="","",IFERROR(B19/$B$20,0)) | D19: =IF(A19="","",IFERROR(AVERAGEIFS('Animais'!$P$6:$P$1005,'Animais'!$M$6:$M$1005,A19,'Animais'!$N$6:$N$1005,"Ativo"),0)) | E19: =IF(A19="","",SUMIFS('Animais'!$P$6:$P$1005,'Animais'!$M$6:$M$1005,A19,'Animais'!$N$6:$N$1005,"Ativo")) | F19: =IF(A19="","",IFERROR(AVERAGEIFS('Animais'!$Q$6:$Q$1005,'Animais'!$M$6:$M$1005,A19,'Animais'!$N$6:$N$1005,"Ativo"),0))
A20: TOTAL ATIVO | B20: =SUM(B7:B19) | C20: =IFERROR(B20/B20,0) | D20: =IFERROR(AVERAGEIFS('Animais'!$P$6:$P$1005,'Animais'!$N$6:$N$1005,"Ativo"),0) | E20: =SUM(E7:E19) | F20: =IFERROR(AVERAGEIFS('Animais'!$Q$6:$Q$1005,'Animais'!$N$6:$N$1005,"Ativo"),0)
A22: Ativos sem categoria válida (verifique sexo/nascimento): | E22: =COUNTIFS('Animais'!$N$6:$N$1005,"Ativo")-B20
A24: Movimentações no ano de análise
A25: Tipo | B25: Cabeças | C25: Valor total (R$) | D25: Peso total (kg) | E25: R$ médio por cabeça
A26: Nascimento | B26: =COUNTIFS('Movimentações'!$B$6:$B$1505,A26,'Movimentações'!$I$6:$I$1505,Config!$B$7) | C26: =SUMIFS('Movimentações'!$E$6:$E$1505,'Movimentações'!$B$6:$B$1505,A26,'Movimentações'!$I$6:$I$1505,Config!$B$7) | D26: =SUMIFS('Movimentações'!$D$6:$D$1505,'Movimentações'!$B$6:$B$1505,A26,'Movimentações'!$I$6:$I$1505,Config!$B$7) | E26: =IFERROR(C26/B26,0)
A27: Compra | B27: =COUNTIFS('Movimentações'!$B$6:$B$1505,A27,'Movimentações'!$I$6:$I$1505,Config!$B$7) | C27: =SUMIFS('Movimentações'!$E$6:$E$1505,'Movimentações'!$B$6:$B$1505,A27,'Movimentações'!$I$6:$I$1505,Config!$B$7) | D27: =SUMIFS('Movimentações'!$D$6:$D$1505,'Movimentações'!$B$6:$B$1505,A27,'Movimentações'!$I$6:$I$1505,Config!$B$7) | E27: =IFERROR(C27/B27,0)
A28: Venda | B28: =COUNTIFS('Movimentações'!$B$6:$B$1505,A28,'Movimentações'!$I$6:$I$1505,Config!$B$7) | C28: =SUMIFS('Movimentações'!$E$6:$E$1505,'Movimentações'!$B$6:$B$1505,A28,'Movimentações'!$I$6:$I$1505,Config!$B$7) | D28: =SUMIFS('Movimentações'!$D$6:$D$1505,'Movimentações'!$B$6:$B$1505,A28,'Movimentações'!$I$6:$I$1505,Config!$B$7) | E28: =IFERROR(C28/B28,0)
A29: Morte | B29: =COUNTIFS('Movimentações'!$B$6:$B$1505,A29,'Movimentações'!$I$6:$I$1505,Config!$B$7) | C29: =SUMIFS('Movimentações'!$E$6:$E$1505,'Movimentações'!$B$6:$B$1505,A29,'Movimentações'!$I$6:$I$1505,Config!$B$7) | D29: =SUMIFS('Movimentações'!$D$6:$D$1505,'Movimentações'!$B$6:$B$1505,A29,'Movimentações'!$I$6:$I$1505,Config!$B$7) | E29: =IFERROR(C29/B29,0)
A31: ="Ano de análise: "&Config!B7

Sheet Exemplo
A1: Exemplo preenchido (dados fictícios)
A2: Veja como a gestão do rebanho funciona antes de cadastrar seus animais
A3: EXEMPLO — TODOS OS DADOS DESTA ABA SÃO FICTÍCIOS, criados apenas para demonstrar o funcionamento. Não use como referência de preços, custos ou produtividade.
A5: Data de referência do exemplo: | D5: 46295 | F5: (as categorias usam as faixas da aba Config)
A7: Animais (exemplo)
A8: Brinco | B8: Sexo | C8: Nascimento | D8: Data entrada | E8: Peso entrada (kg) | F8: Categ. manual | G8: Categoria | H8: Status | I8: Última pesagem | J8: Último peso (kg) | K8: GMD (kg/dia)
A9: 001 | B9: F | C9: 43740 | D9: 43740 | E9: 32 | G9: =IF(F9<>"",F9,IFERROR(IF(B9="M",INDEX(Config!$B$11:$B$14,MATCH(DATEDIF(C9,$D$5,"m"),Config!$A$11:$A$14,1)),INDEX(Config!$C$11:$C$14,MATCH(DATEDIF(C9,$D$5,"m"),Config!$A$11:$A$14,1))),"Verificar")) | H9: =IF(COUNTIFS($C$37:$C$43,A9,$B$37:$B$43,"Venda")>0,"Vendido",IF(COUNTIFS($C$37:$C$43,A9,$B$37:$B$43,"Morte")>0,"Morto","Ativo")) | I9: =IF(COUNTIF($B$22:$B$33,A9)=0,"",SUMPRODUCT(MAX(($B$22:$B$33=A9)*$A$22:$A$33))) | J9: =IF(I9="",E9,IFERROR(AVERAGEIFS($C$22:$C$33,$B$22:$B$33,A9,$A$22:$A$33,I9),"")) | K9: =IF(I9="","",IFERROR((J9-E9)/(I9-D9),""))
A10: 002 | B10: F | C10: 44089 | D10: 44089 | E10: 30 | G10: =IF(F10<>"",F10,IFERROR(IF(B10="M",INDEX(Config!$B$11:$B$14,MATCH(DATEDIF(C10,$D$5,"m"),Config!$A$11:$A$14,1)),INDEX(Config!$C$11:$C$14,MATCH(DATEDIF(C10,$D$5,"m"),Config!$A$11:$A$14,1))),"Verificar")) | H10: =IF(COUNTIFS($C$37:$C$43,A10,$B$37:$B$43,"Venda")>0,"Vendido",IF(COUNTIFS($C$37:$C$43,A10,$B$37:$B$43,"Morte")>0,"Morto","Ativo")) | I10: =IF(COUNTIF($B$22:$B$33,A10)=0,"",SUMPRODUCT(MAX(($B$22:$B$33=A10)*$A$22:$A$33))) | J10: =IF(I10="",E10,IFERROR(AVERAGEIFS($C$22:$C$33,$B$22:$B$33,A10,$A$22:$A$33,I10),"")) | K10: =IF(I10="","",IFERROR((J10-E10)/(I10-D10),""))
A11: 003 | B11: M | C11: 43332 | D11: 44326 | E11: 520 | F11: Touro | G11: =IF(F11<>"",F11,IFERROR(IF(B11="M",INDEX(Config!$B$11:$B$14,MATCH(DATEDIF(C11,$D$5,"m"),Config!$A$11:$A$14,1)),INDEX(Config!$C$11:$C$14,MATCH(DATEDIF(C11,$D$5,"m"),Config!$A$11:$A$14,1))),"Verificar")) | H11: =IF(COUNTIFS($C$37:$C$43,A11,$B$37:$B$43,"Venda")>0,"Vendido",IF(COUNTIFS($C$37:$C$43,A11,$B$37:$B$43,"Morte")>0,"Morto","Ativo")) | I11: =IF(COUNTIF($B$22:$B$33,A11)=0,"",SUMPRODUCT(MAX(($B$22:$B$33=A11)*$A$22:$A$33))) | J11: =IF(I11="",E11,IFERROR(AVERAGEIFS($C$22:$C$33,$B$22:$B$33,A11,$A$22:$A$33,I11),"")) | K11: =IF(I11="","",IFERROR((J11-E11)/(I11-D11),""))
A12: 004 | B12: M | C12: 45935 | D12: 45935 | E12: 31 | G12: =IF(F12<>"",F12,IFERROR(IF(B12="M",INDEX(Config!$B$11:$B$14,MATCH(DATEDIF(C12,$D$5,"m"),Config!$A$11:$A$14,1)),INDEX(Config!$C$11:$C$14,MATCH(DATEDIF(C12,$D$5,"m"),Config!$A$11:$A$14,1))),"Verificar")) | H12: =IF(COUNTIFS($C$37:$C$43,A12,$B$37:$B$43,"Venda")>0,"Vendido",IF(COUNTIFS($C$37:$C$43,A12,$B$37:$B$43,"Morte")>0,"Morto","Ativo")) | I12: =IF(COUNTIF($B$22:$B$33,A12)=0,"",SUMPRODUCT(MAX(($B$22:$B$33=A12)*$A$22:$A$33))) | J12: =IF(I12="",E12,IFERROR(AVERAGEIFS($C$22:$C$33,$B$22:$B$33,A12,$A$22:$A$33,I12),"")) | K12: =IF(I12="","",IFERROR((J12-E12)/(I12-D12),""))
A13: 005 | B13: F | C13: 45973 | D13: 45973 | E13: 29 | G13: =IF(F13<>"",F13,IFERROR(IF(B13="M",INDEX(Config!$B$11:$B$14,MATCH(DATEDIF(C13,$D$5,"m"),Config!$A$11:$A$14,1)),INDEX(Config!$C$11:$C$14,MATCH(DATEDIF(C13,$D$5,"m"),Config!$A$11:$A$14,1))),"Verificar")) | H13: =IF(COUNTIFS($C$37:$C$43,A13,$B$37:$B$43,"Venda")>0,"Vendido",IF(COUNTIFS($C$37:$C$43,A13,$B$37:$B$43,"Morte")>0,"Morto","Ativo")) | I13: =IF(COUNTIF($B$22:$B$33,A13)=0,"",SUMPRODUCT(MAX(($B$22:$B$33=A13)*$A$22:$A$33))) | J13: =IF(I13="",E13,IFERROR(AVERAGEIFS($C$22:$C$33,$B$22:$B$33,A13,$A$22:$A$33,I13),"")) | K13: =IF(I13="","",IFERROR((J13-E13)/(I13-D13),""))
A14: 006 | B14: M | C14: 45627 | D14: 45870 | E14: 210 | G14: =IF(F14<>"",F14,IFERROR(IF(B14="M",INDEX(Config!$B$11:$B$14,MATCH(DATEDIF(C14,$D$5,"m"),Config!$A$11:$A$14,1)),INDEX(Config!$C$11:$C$14,MATCH(DATEDIF(C14,$D$5,"m"),Config!$A$11:$A$14,1))),"Verificar")) | H14: =IF(COUNTIFS($C$37:$C$43,A14,$B$37:$B$43,"Venda")>0,"Vendido",IF(COUNTIFS($C$37:$C$43,A14,$B$37:$B$43,"Morte")>0,"Morto","Ativo")) | I14: =IF(COUNTIF($B$22:$B$33,A14)=0,"",SUMPRODUCT(MAX(($B$22:$B$33=A14)*$A$22:$A$33))) | J14: =IF(I14="",E14,IFERROR(AVERAGEIFS($C$22:$C$33,$B$22:$B$33,A14,$A$22:$A$33,I14),"")) | K14: =IF(I14="","",IFERROR((J14-E14)/(I14-D14),""))
A15: 007 | B15: M | C15: 45616 | D15: 45870 | E15: 205 | G15: =IF(F15<>"",F15,IFERROR(IF(B15="M",INDEX(Config!$B$11:$B$14,MATCH(DATEDIF(C15,$D$5,"m"),Config!$A$11:$A$14,1)),INDEX(Config!$C$11:$C$14,MATCH(DATEDIF(C15,$D$5,"m"),Config!$A$11:$A$14,1))),"Verificar")) | H15: =IF(COUNTIFS($C$37:$C$43,A15,$B$37:$B$43,"Venda")>0,"Vendido",IF(COUNTIFS($C$37:$C$43,A15,$B$37:$B$43,"Morte")>0,"Morto","Ativo")) | I15: =IF(COUNTIF($B$22:$B$33,A15)=0,"",SUMPRODUCT(MAX(($B$22:$B$33=A15)*$A$22:$A$33))) | J15: =IF(I15="",E15,IFERROR(AVERAGEIFS($C$22:$C$33,$B$22:$B$33,A15,$A$22:$A$33,I15),"")) | K15: =IF(I15="","",IFERROR((J15-E15)/(I15-D15),""))
A16: 008 | B16: F | C16: 45354 | D16: 45354 | E16: 30 | G16: =IF(F16<>"",F16,IFERROR(IF(B16="M",INDEX(Config!$B$11:$B$14,MATCH(DATEDIF(C16,$D$5,"m"),Config!$A$11:$A$14,1)),INDEX(Config!$C$11:$C$14,MATCH(DATEDIF(C16,$D$5,"m"),Config!$A$11:$A$14,1))),"Verificar")) | H16: =IF(COUNTIFS($C$37:$C$43,A16,$B$37:$B$43,"Venda")>0,"Vendido",IF(COUNTIFS($C$37:$C$43,A16,$B$37:$B$43,"Morte")>0,"Morto","Ativo")) | I16: =IF(COUNTIF($B$22:$B$33,A16)=0,"",SUMPRODUCT(MAX(($B$22:$B$33=A16)*$A$22:$A$33))) | J16: =IF(I16="",E16,IFERROR(AVERAGEIFS($C$22:$C$33,$B$22:$B$33,A16,$A$22:$A$33,I16),"")) | K16: =IF(I16="","",IFERROR((J16-E16)/(I16-D16),""))
A17: 009 | B17: M | C17: 45178 | D17: 45178 | E17: 33 | G17: =IF(F17<>"",F17,IFERROR(IF(B17="M",INDEX(Config!$B$11:$B$14,MATCH(DATEDIF(C17,$D$5,"m"),Config!$A$11:$A$14,1)),INDEX(Config!$C$11:$C$14,MATCH(DATEDIF(C17,$D$5,"m"),Config!$A$11:$A$14,1))),"Verificar")) | H17: =IF(COUNTIFS($C$37:$C$43,A17,$B$37:$B$43,"Venda")>0,"Vendido",IF(COUNTIFS($C$37:$C$43,A17,$B$37:$B$43,"Morte")>0,"Morto","Ativo")) | I17: =IF(COUNTIF($B$22:$B$33,A17)=0,"",SUMPRODUCT(MAX(($B$22:$B$33=A17)*$A$22:$A$33))) | J17: =IF(I17="",E17,IFERROR(AVERAGEIFS($C$22:$C$33,$B$22:$B$33,A17,$A$22:$A$33,I17),"")) | K17: =IF(I17="","",IFERROR((J17-E17)/(I17-D17),""))
A18: 010 | B18: M | C18: 45575 | D18: 45870 | E18: 215 | G18: =IF(F18<>"",F18,IFERROR(IF(B18="M",INDEX(Config!$B$11:$B$14,MATCH(DATEDIF(C18,$D$5,"m"),Config!$A$11:$A$14,1)),INDEX(Config!$C$11:$C$14,MATCH(DATEDIF(C18,$D$5,"m"),Config!$A$11:$A$14,1))),"Verificar")) | H18: =IF(COUNTIFS($C$37:$C$43,A18,$B$37:$B$43,"Venda")>0,"Vendido",IF(COUNTIFS($C$37:$C$43,A18,$B$37:$B$43,"Morte")>0,"Morto","Ativo")) | I18: =IF(COUNTIF($B$22:$B$33,A18)=0,"",SUMPRODUCT(MAX(($B$22:$B$33=A18)*$A$22:$A$33))) | J18: =IF(I18="",E18,IFERROR(AVERAGEIFS($C$22:$C$33,$B$22:$B$33,A18,$A$22:$A$33,I18),"")) | K18: =IF(I18="","",IFERROR((J18-E18)/(I18-D18),""))
A20: Pesagens (exemplo) | G20: Inventário do exemplo (ativos)
A21: Data | B21: Brinco | C21: Peso (kg) | G21: Categoria | H21: Cabeças | I21: Peso médio (kg)
A22: 46082 | B22: 004 | C22: 140 | G22: =Listas!A2 | H22: =IF(G22="","",COUNTIFS($G$9:$G$18,G22,$H$9:$H$18,"Ativo")) | I22: =IF(G22="","",IFERROR(AVERAGEIFS($J$9:$J$18,$G$9:$G$18,G22,$H$9:$H$18,"Ativo"),0))
A23: 46265 | B23: 004 | C23: 225 | G23: =Listas!A3 | H23: =IF(G23="","",COUNTIFS($G$9:$G$18,G23,$H$9:$H$18,"Ativo")) | I23: =IF(G23="","",IFERROR(AVERAGEIFS($J$9:$J$18,$G$9:$G$18,G23,$H$9:$H$18,"Ativo"),0))
A24: 46082 | B24: 005 | C24: 120 | G24: =Listas!A4 | H24: =IF(G24="","",COUNTIFS($G$9:$G$18,G24,$H$9:$H$18,"Ativo")) | I24: =IF(G24="","",IFERROR(AVERAGEIFS($J$9:$J$18,$G$9:$G$18,G24,$H$9:$H$18,"Ativo"),0))
A25: 46265 | B25: 005 | C25: 200 | G25: =Listas!A5 | H25: =IF(G25="","",COUNTIFS($G$9:$G$18,G25,$H$9:$H$18,"Ativo")) | I25: =IF(G25="","",IFERROR(AVERAGEIFS($J$9:$J$18,$G$9:$G$18,G25,$H$9:$H$18,"Ativo"),0))
A26: 46054 | B26: 006 | C26: 300 | G26: =Listas!A6 | H26: =IF(G26="","",COUNTIFS($G$9:$G$18,G26,$H$9:$H$18,"Ativo")) | I26: =IF(G26="","",IFERROR(AVERAGEIFS($J$9:$J$18,$G$9:$G$18,G26,$H$9:$H$18,"Ativo"),0))
A27: 46265 | B27: 006 | C27: 390 | G27: =Listas!A7 | H27: =IF(G27="","",COUNTIFS($G$9:$G$18,G27,$H$9:$H$18,"Ativo")) | I27: =IF(G27="","",IFERROR(AVERAGEIFS($J$9:$J$18,$G$9:$G$18,G27,$H$9:$H$18,"Ativo"),0))
A28: 46054 | B28: 007 | C28: 290 | G28: =Listas!A8 | H28: =IF(G28="","",COUNTIFS($G$9:$G$18,G28,$H$9:$H$18,"Ativo")) | I28: =IF(G28="","",IFERROR(AVERAGEIFS($J$9:$J$18,$G$9:$G$18,G28,$H$9:$H$18,"Ativo"),0))
A29: 46265 | B29: 007 | C29: 372 | G29: =Listas!A9 | H29: =IF(G29="","",COUNTIFS($G$9:$G$18,G29,$H$9:$H$18,"Ativo")) | I29: =IF(G29="","",IFERROR(AVERAGEIFS($J$9:$J$18,$G$9:$G$18,G29,$H$9:$H$18,"Ativo"),0))
A30: 46054 | B30: 010 | C30: 305 | G30: =Listas!A10 | H30: =IF(G30="","",COUNTIFS($G$9:$G$18,G30,$H$9:$H$18,"Ativo")) | I30: =IF(G30="","",IFERROR(AVERAGEIFS($J$9:$J$18,$G$9:$G$18,G30,$H$9:$H$18,"Ativo"),0))
A31: 46203 | B31: 010 | C31: 368 | G31: =Listas!A11 | H31: =IF(G31="","",COUNTIFS($G$9:$G$18,G31,$H$9:$H$18,"Ativo")) | I31: =IF(G31="","",IFERROR(AVERAGEIFS($J$9:$J$18,$G$9:$G$18,G31,$H$9:$H$18,"Ativo"),0))
A32: 46265 | B32: 008 | C32: 330 | G32: =Listas!A12 | H32: =IF(G32="","",COUNTIFS($G$9:$G$18,G32,$H$9:$H$18,"Ativo")) | I32: =IF(G32="","",IFERROR(AVERAGEIFS($J$9:$J$18,$G$9:$G$18,G32,$H$9:$H$18,"Ativo"),0))
A33: 46265 | B33: 009 | C33: 480 | G33: =Listas!A13 | H33: =IF(G33="","",COUNTIFS($G$9:$G$18,G33,$H$9:$H$18,"Ativo")) | I33: =IF(G33="","",IFERROR(AVERAGEIFS($J$9:$J$18,$G$9:$G$18,G33,$H$9:$H$18,"Ativo"),0))
G34: =Listas!A14 | H34: =IF(G34="","",COUNTIFS($G$9:$G$18,G34,$H$9:$H$18,"Ativo")) | I34: =IF(G34="","",IFERROR(AVERAGEIFS($J$9:$J$18,$G$9:$G$18,G34,$H$9:$H$18,"Ativo"),0))
A35: Movimentações (exemplo) | G35: TOTAL ATIVO | H35: =SUM(H22:H34) | I35: =IFERROR(AVERAGEIFS($J$9:$J$18,$H$9:$H$18,"Ativo"),0)
A36: Data | B36: Tipo | C36: Brinco | D36: Peso (kg) | E36: Valor (R$) | F36: Obs. | G36: Conferência (ativos − total): | I36: =COUNTIF($H$9:$H$18,"Ativo")-H35
A37: 45935 | B37: Nascimento | C37: 004 | D37: 31 | E37: 0
A38: 45973 | B38: Nascimento | C38: 005 | D38: 29 | E38: 0
A39: 45870 | B39: Compra | C39: 006 | D39: 210 | E39: 2600 | F39: Fornecedor fictício
A40: 45870 | B40: Compra | C40: 007 | D40: 205 | E40: 2550 | F40: Fornecedor fictício
A41: 45870 | B41: Compra | C41: 010 | D41: 215 | E41: 2650 | F41: Fornecedor fictício
A42: 46218 | B42: Venda | C42: 009 | D42: 470 | E42: 6200 | F42: Comprador fictício
A43: 46223 | B43: Morte | C43: 010 | D43: 370 | E43: 0 | F43: Causa a registrar
